[{"ts":1608207649154,"particle":"pm_10_0","value":20,"max_value":62},{"ts":1608208050722,"particle":"pm_10_0","value":18,"max_value":62},{"ts":1608208452214,"particle":"pm_10_0","value":15,"max_value":62},{"ts":1608208853684,"particle":"pm_10_0","value":17,"max_value":62},{"ts":1608209255373,"particle":"pm_10_0","value":16,"max_value":62},{"ts":1608209656386,"particle":"pm_10_0","value":14,"max_value":62},{"ts":1608210057540,"particle":"pm_10_0","value":12,"max_value":62},{"ts":1608210458804,"particle":"pm_10_0","value":11,"max_value":62},{"ts":1608210861477,"particle":"pm_10_0","value":12,"max_value":62},{"ts":1608211264801,"particle":"pm_10_0","value":14,"max_value":62},{"ts":1608211666302,"particle":"pm_10_0","value":13,"max_value":62},{"ts":1608212068171,"particle":"pm_10_0","value":14,"max_value":62},{"ts":1608212470325,"particle":"pm_10_0","value":14,"max_value":62},{"ts":1608212872959,"particle":"pm_10_0","value":14,"max_value":62},{"ts":1608213275632,"particle":"pm_10_0","value":15,"max_value":62},{"ts":1608213677154,"particle":"pm_10_0","value":10,"max_value":62},{"ts":1608214079410,"particle":"pm_10_0","value":10,"max_value":62},{"ts":1608214481691,"particle":"pm_10_0","value":11,"max_value":62},{"ts":1608214884340,"particle":"pm_10_0","value":10,"max_value":62},{"ts":1608215286540,"particle":"pm_10_0","value":9,"max_value":62},{"ts":1608215688941,"particle":"pm_10_0","value":9,"max_value":62},{"ts":1608216092745,"particle":"pm_10_0","value":9,"max_value":62},{"ts":1608216494341,"particle":"pm_10_0","value":7,"max_value":62},{"ts":1608216895610,"particle":"pm_10_0","value":9,"max_value":62},{"ts":1608217296428,"particle":"pm_10_0","value":7,"max_value":62},{"ts":1608217697923,"particle":"pm_10_0","value":10,"max_value":62},{"ts":1608218099203,"particle":"pm_10_0","value":8,"max_value":62},{"ts":1608218500536,"particle":"pm_10_0","value":7,"max_value":62},{"ts":1608218901665,"particle":"pm_10_0","value":7,"max_value":62},{"ts":1608219304367,"particle":"pm_10_0","value":6,"max_value":62},{"ts":1608219705412,"particle":"pm_10_0","value":6,"max_value":62},{"ts":1608220106675,"particle":"pm_10_0","value":6,"max_value":62},{"ts":1608220508133,"particle":"pm_10_0","value":7,"max_value":62},{"ts":1608220909537,"particle":"pm_10_0","value":4,"max_value":62},{"ts":1608221311403,"particle":"pm_10_0","value":6,"max_value":62},{"ts":1608221714103,"particle":"pm_10_0","value":5,"max_value":62},{"ts":1608222114857,"particle":"pm_10_0","value":4,"max_value":62},{"ts":1608222516589,"particle":"pm_10_0","value":5,"max_value":62},{"ts":1608222918243,"particle":"pm_10_0","value":6,"max_value":62},{"ts":1608223320052,"particle":"pm_10_0","value":6,"max_value":62},{"ts":1608223721842,"particle":"pm_10_0","value":6,"max_value":62},{"ts":1608224123580,"particle":"pm_10_0","value":6,"max_value":62},{"ts":1608224525231,"particle":"pm_10_0","value":5,"max_value":62},{"ts":1608224928563,"particle":"pm_10_0","value":6,"max_value":62},{"ts":1608225330411,"particle":"pm_10_0","value":6,"max_value":62},{"ts":1608225732511,"particle":"pm_10_0","value":6,"max_value":62},{"ts":1608226134571,"particle":"pm_10_0","value":6,"max_value":62},{"ts":1608226535370,"particle":"pm_10_0","value":6,"max_value":62},{"ts":1608226936238,"particle":"pm_10_0","value":6,"max_value":62},{"ts":1608227337675,"particle":"pm_10_0","value":7,"max_value":62},{"ts":1608227738603,"particle":"pm_10_0","value":6,"max_value":62},{"ts":1608228139548,"particle":"pm_10_0","value":7,"max_value":62},{"ts":1608228542663,"particle":"pm_10_0","value":5,"max_value":62},{"ts":1608228944051,"particle":"pm_10_0","value":8,"max_value":62},{"ts":1608229346775,"particle":"pm_10_0","value":6,"max_value":62},{"ts":1608229747957,"particle":"pm_10_0","value":7,"max_value":62},{"ts":1608230149223,"particle":"pm_10_0","value":8,"max_value":62},{"ts":1608230550664,"particle":"pm_10_0","value":7,"max_value":62},{"ts":1608230953076,"particle":"pm_10_0","value":9,"max_value":62},{"ts":1608231354555,"particle":"pm_10_0","value":8,"max_value":62},{"ts":1608231755959,"particle":"pm_10_0","value":10,"max_value":62},{"ts":1608232158768,"particle":"pm_10_0","value":15,"max_value":62},{"ts":1608232560989,"particle":"pm_10_0","value":12,"max_value":62},{"ts":1608232964122,"particle":"pm_10_0","value":12,"max_value":62},{"ts":1608233365981,"particle":"pm_10_0","value":10,"max_value":62},{"ts":1608233767770,"particle":"pm_10_0","value":10,"max_value":62},{"ts":1608234169570,"particle":"pm_10_0","value":15,"max_value":62},{"ts":1608234573301,"particle":"pm_10_0","value":12,"max_value":62},{"ts":1608234975154,"particle":"pm_10_0","value":11,"max_value":62},{"ts":1608235378401,"particle":"pm_10_0","value":11,"max_value":62},{"ts":1608235780532,"particle":"pm_10_0","value":13,"max_value":62},{"ts":1608236181489,"particle":"pm_10_0","value":11,"max_value":62},{"ts":1608236582895,"particle":"pm_10_0","value":11,"max_value":62},{"ts":1608236983722,"particle":"pm_10_0","value":12,"max_value":62},{"ts":1608237385609,"particle":"pm_10_0","value":14,"max_value":62},{"ts":1608237786477,"particle":"pm_10_0","value":12,"max_value":62},{"ts":1608238187538,"particle":"pm_10_0","value":12,"max_value":62},{"ts":1608238588551,"particle":"pm_10_0","value":13,"max_value":62},{"ts":1608238989580,"particle":"pm_10_0","value":13,"max_value":62},{"ts":1608239394693,"particle":"pm_10_0","value":16,"max_value":62},{"ts":1608239796393,"particle":"pm_10_0","value":19,"max_value":62},{"ts":1608240198518,"particle":"pm_10_0","value":13,"max_value":62},{"ts":1608240600099,"particle":"pm_10_0","value":13,"max_value":62},{"ts":1608241001429,"particle":"pm_10_0","value":11,"max_value":62},{"ts":1608241403217,"particle":"pm_10_0","value":13,"max_value":62},{"ts":1608241805228,"particle":"pm_10_0","value":12,"max_value":62},{"ts":1608242207378,"particle":"pm_10_0","value":14,"max_value":62},{"ts":1608242609621,"particle":"pm_10_0","value":15,"max_value":62},{"ts":1608243011452,"particle":"pm_10_0","value":12,"max_value":62},{"ts":1608243413007,"particle":"pm_10_0","value":11,"max_value":62},{"ts":1608243815064,"particle":"pm_10_0","value":12,"max_value":62},{"ts":1608244216634,"particle":"pm_10_0","value":13,"max_value":62},{"ts":1608244618283,"particle":"pm_10_0","value":12,"max_value":62},{"ts":1608245019992,"particle":"pm_10_0","value":12,"max_value":62},{"ts":1608245421790,"particle":"pm_10_0","value":11,"max_value":62},{"ts":1608245823381,"particle":"pm_10_0","value":10,"max_value":62},{"ts":1608246224892,"particle":"pm_10_0","value":11,"max_value":62},{"ts":1608246625678,"particle":"pm_10_0","value":10,"max_value":62},{"ts":1608247028517,"particle":"pm_10_0","value":15,"max_value":62},{"ts":1608247429871,"particle":"pm_10_0","value":10,"max_value":62},{"ts":1608247832873,"particle":"pm_10_0","value":14,"max_value":62},{"ts":1608248233859,"particle":"pm_10_0","value":11,"max_value":62},{"ts":1608248635074,"particle":"pm_10_0","value":9,"max_value":62},{"ts":1608249036619,"particle":"pm_10_0","value":11,"max_value":62},{"ts":1608249844695,"particle":"pm_10_0","value":12,"max_value":62},{"ts":1608250245776,"particle":"pm_10_0","value":11,"max_value":62},{"ts":1608250647507,"particle":"pm_10_0","value":9,"max_value":62},{"ts":1608251049128,"particle":"pm_10_0","value":10,"max_value":62},{"ts":1608251451016,"particle":"pm_10_0","value":11,"max_value":62},{"ts":1608251852590,"particle":"pm_10_0","value":11,"max_value":62},{"ts":1608252254880,"particle":"pm_10_0","value":10,"max_value":62},{"ts":1608252656441,"particle":"pm_10_0","value":9,"max_value":62},{"ts":1608253057967,"particle":"pm_10_0","value":7,"max_value":62},{"ts":1608253460941,"particle":"pm_10_0","value":12,"max_value":62},{"ts":1608253862834,"particle":"pm_10_0","value":14,"max_value":62},{"ts":1608254264523,"particle":"pm_10_0","value":11,"max_value":62},{"ts":1608254666050,"particle":"pm_10_0","value":10,"max_value":62},{"ts":1608255067832,"particle":"pm_10_0","value":9,"max_value":62},{"ts":1608255470051,"particle":"pm_10_0","value":12,"max_value":62},{"ts":1608255874153,"particle":"pm_10_0","value":12,"max_value":62},{"ts":1608256276210,"particle":"pm_10_0","value":9,"max_value":62},{"ts":1608256677274,"particle":"pm_10_0","value":10,"max_value":62},{"ts":1608257078603,"particle":"pm_10_0","value":6,"max_value":62},{"ts":1608257481252,"particle":"pm_10_0","value":8,"max_value":62},{"ts":1608257883857,"particle":"pm_10_0","value":9,"max_value":62},{"ts":1608258285009,"particle":"pm_10_0","value":7,"max_value":62},{"ts":1608258686063,"particle":"pm_10_0","value":8,"max_value":62},{"ts":1608259087133,"particle":"pm_10_0","value":9,"max_value":62},{"ts":1608259488460,"particle":"pm_10_0","value":7,"max_value":62},{"ts":1608259889667,"particle":"pm_10_0","value":6,"max_value":62},{"ts":1608260291078,"particle":"pm_10_0","value":7,"max_value":62},{"ts":1608260693040,"particle":"pm_10_0","value":10,"max_value":62},{"ts":1608261094988,"particle":"pm_10_0","value":7,"max_value":62},{"ts":1608261496568,"particle":"pm_10_0","value":7,"max_value":62},{"ts":1608261898435,"particle":"pm_10_0","value":6,"max_value":62},{"ts":1608262300169,"particle":"pm_10_0","value":6,"max_value":62},{"ts":1608262701938,"particle":"pm_10_0","value":6,"max_value":62},{"ts":1608263105179,"particle":"pm_10_0","value":7,"max_value":62},{"ts":1608263508270,"particle":"pm_10_0","value":8,"max_value":62},{"ts":1608263910108,"particle":"pm_10_0","value":6,"max_value":62},{"ts":1608264311930,"particle":"pm_10_0","value":5,"max_value":62},{"ts":1608264713753,"particle":"pm_10_0","value":6,"max_value":62},{"ts":1608265114653,"particle":"pm_10_0","value":4,"max_value":62},{"ts":1608265516562,"particle":"pm_10_0","value":5,"max_value":62},{"ts":1608265918222,"particle":"pm_10_0","value":5,"max_value":62},{"ts":1608266319068,"particle":"pm_10_0","value":4,"max_value":62},{"ts":1608266719848,"particle":"pm_10_0","value":4,"max_value":62},{"ts":1608267120698,"particle":"pm_10_0","value":4,"max_value":62},{"ts":1608267521929,"particle":"pm_10_0","value":4,"max_value":62},{"ts":1608267922945,"particle":"pm_10_0","value":6,"max_value":62},{"ts":1608268324531,"particle":"pm_10_0","value":6,"max_value":62},{"ts":1608268725602,"particle":"pm_10_0","value":5,"max_value":62},{"ts":1608269126800,"particle":"pm_10_0","value":4,"max_value":62},{"ts":1608269528066,"particle":"pm_10_0","value":4,"max_value":62},{"ts":1608269929292,"particle":"pm_10_0","value":3,"max_value":62},{"ts":1608270332191,"particle":"pm_10_0","value":4,"max_value":62},{"ts":1608270733613,"particle":"pm_10_0","value":3,"max_value":62},{"ts":1608271136572,"particle":"pm_10_0","value":4,"max_value":62},{"ts":1608271537937,"particle":"pm_10_0","value":5,"max_value":62},{"ts":1608271939473,"particle":"pm_10_0","value":4,"max_value":62},{"ts":1608272341101,"particle":"pm_10_0","value":4,"max_value":62},{"ts":1608272742764,"particle":"pm_10_0","value":4,"max_value":62},{"ts":1608273144532,"particle":"pm_10_0","value":5,"max_value":62},{"ts":1608273546285,"particle":"pm_10_0","value":4,"max_value":62},{"ts":1608273948890,"particle":"pm_10_0","value":6,"max_value":62},{"ts":1608274350720,"particle":"pm_10_0","value":4,"max_value":62},{"ts":1608274752491,"particle":"pm_10_0","value":5,"max_value":62},{"ts":1608275154174,"particle":"pm_10_0","value":4,"max_value":62},{"ts":1608275556681,"particle":"pm_10_0","value":4,"max_value":62},{"ts":1608275957605,"particle":"pm_10_0","value":4,"max_value":62},{"ts":1608276358262,"particle":"pm_10_0","value":5,"max_value":62},{"ts":1608276758914,"particle":"pm_10_0","value":7,"max_value":62},{"ts":1608277161116,"particle":"pm_10_0","value":5,"max_value":62},{"ts":1608277562060,"particle":"pm_10_0","value":7,"max_value":62},{"ts":1608277963298,"particle":"pm_10_0","value":9,"max_value":62},{"ts":1608278364342,"particle":"pm_10_0","value":8,"max_value":62},{"ts":1608278765364,"particle":"pm_10_0","value":6,"max_value":62},{"ts":1608279166104,"particle":"pm_10_0","value":7,"max_value":62},{"ts":1608279567390,"particle":"pm_10_0","value":5,"max_value":62},{"ts":1608279970534,"particle":"pm_10_0","value":5,"max_value":62},{"ts":1608280372087,"particle":"pm_10_0","value":6,"max_value":62},{"ts":1608280773717,"particle":"pm_10_0","value":6,"max_value":62},{"ts":1608281175989,"particle":"pm_10_0","value":7,"max_value":62},{"ts":1608281577632,"particle":"pm_10_0","value":5,"max_value":62},{"ts":1608281980919,"particle":"pm_10_0","value":6,"max_value":62},{"ts":1608282384594,"particle":"pm_10_0","value":7,"max_value":62},{"ts":1608282787983,"particle":"pm_10_0","value":6,"max_value":62},{"ts":1608283189940,"particle":"pm_10_0","value":6,"max_value":62},{"ts":1608283591882,"particle":"pm_10_0","value":6,"max_value":62},{"ts":1608283997911,"particle":"pm_10_0","value":6,"max_value":62},{"ts":1608284399632,"particle":"pm_10_0","value":5,"max_value":62},{"ts":1608284801640,"particle":"pm_10_0","value":7,"max_value":62},{"ts":1608285203922,"particle":"pm_10_0","value":5,"max_value":62},{"ts":1608285607982,"particle":"pm_10_0","value":6,"max_value":62},{"ts":1608286010730,"particle":"pm_10_0","value":8,"max_value":62},{"ts":1608286411873,"particle":"pm_10_0","value":6,"max_value":62},{"ts":1608286816519,"particle":"pm_10_0","value":7,"max_value":62},{"ts":1608287217624,"particle":"pm_10_0","value":6,"max_value":62},{"ts":1608287618929,"particle":"pm_10_0","value":6,"max_value":62},{"ts":1608288020104,"particle":"pm_10_0","value":5,"max_value":62},{"ts":1608288421448,"particle":"pm_10_0","value":7,"max_value":62},{"ts":1608288824442,"particle":"pm_10_0","value":6,"max_value":62},{"ts":1608289226023,"particle":"pm_10_0","value":6,"max_value":62},{"ts":1608289627832,"particle":"pm_10_0","value":4,"max_value":62},{"ts":1608290029641,"particle":"pm_10_0","value":7,"max_value":62},{"ts":1608290431469,"particle":"pm_10_0","value":5,"max_value":62},{"ts":1608290833215,"particle":"pm_10_0","value":5,"max_value":62},{"ts":1608291236457,"particle":"pm_10_0","value":6,"max_value":62},{"ts":1608291638073,"particle":"pm_10_0","value":7,"max_value":62},{"ts":1608292040111,"particle":"pm_10_0","value":6,"max_value":62},{"ts":1608292442308,"particle":"pm_10_0","value":5,"max_value":62},{"ts":1608292843950,"particle":"pm_10_0","value":7,"max_value":62},{"ts":1608293245374,"particle":"pm_10_0","value":8,"max_value":62},{"ts":1608293648772,"particle":"pm_10_0","value":7,"max_value":62},{"ts":1608294050572,"particle":"pm_10_0","value":8,"max_value":62},{"ts":1608294452274,"particle":"pm_10_0","value":7,"max_value":62},{"ts":1608294854104,"particle":"pm_10_0","value":6,"max_value":62},{"ts":1608295256392,"particle":"pm_10_0","value":8,"max_value":62},{"ts":1608295658150,"particle":"pm_10_0","value":7,"max_value":62},{"ts":1608296059004,"particle":"pm_10_0","value":7,"max_value":62},{"ts":1608296461327,"particle":"pm_10_0","value":7,"max_value":62},{"ts":1608296862117,"particle":"pm_10_0","value":6,"max_value":62},{"ts":1608297263273,"particle":"pm_10_0","value":6,"max_value":62},{"ts":1608297665525,"particle":"pm_10_0","value":6,"max_value":62},{"ts":1608298065242,"particle":"pm_10_0","value":6,"max_value":62},{"ts":1608298466290,"particle":"pm_10_0","value":5,"max_value":62},{"ts":1608298867254,"particle":"pm_10_0","value":7,"max_value":62},{"ts":1608299268402,"particle":"pm_10_0","value":7,"max_value":62},{"ts":1608299669651,"particle":"pm_10_0","value":9,"max_value":62},{"ts":1608300070738,"particle":"pm_10_0","value":6,"max_value":62},{"ts":1608300472372,"particle":"pm_10_0","value":7,"max_value":62},{"ts":1608300874235,"particle":"pm_10_0","value":8,"max_value":62},{"ts":1608301276494,"particle":"pm_10_0","value":29,"max_value":62},{"ts":1608301679972,"particle":"pm_10_0","value":44,"max_value":62},{"ts":1608302083093,"particle":"pm_10_0","value":41,"max_value":62},{"ts":1608302487862,"particle":"pm_10_0","value":39,"max_value":62},{"ts":1608302890471,"particle":"pm_10_0","value":43,"max_value":62},{"ts":1608303292971,"particle":"pm_10_0","value":43,"max_value":62},{"ts":1608303697014,"particle":"pm_10_0","value":46,"max_value":62},{"ts":1608304099550,"particle":"pm_10_0","value":46,"max_value":62},{"ts":1608304503520,"particle":"pm_10_0","value":49,"max_value":62},{"ts":1608304906244,"particle":"pm_10_0","value":47,"max_value":62},{"ts":1608305309552,"particle":"pm_10_0","value":47,"max_value":62},{"ts":1608305714343,"particle":"pm_10_0","value":44,"max_value":62},{"ts":1608306115248,"particle":"pm_10_0","value":39,"max_value":62},{"ts":1608306516974,"particle":"pm_10_0","value":42,"max_value":62},{"ts":1608306919095,"particle":"pm_10_0","value":42,"max_value":62},{"ts":1608307321820,"particle":"pm_10_0","value":43,"max_value":62},{"ts":1608307724080,"particle":"pm_10_0","value":41,"max_value":62},{"ts":1608308125978,"particle":"pm_10_0","value":35,"max_value":62},{"ts":1608308526909,"particle":"pm_10_0","value":32,"max_value":62},{"ts":1608308930161,"particle":"pm_10_0","value":32,"max_value":62},{"ts":1608309331908,"particle":"pm_10_0","value":28,"max_value":62},{"ts":1608309733873,"particle":"pm_10_0","value":27,"max_value":62},{"ts":1608310136031,"particle":"pm_10_0","value":27,"max_value":62},{"ts":1608310537076,"particle":"pm_10_0","value":22,"max_value":62},{"ts":1608310940707,"particle":"pm_10_0","value":25,"max_value":62},{"ts":1608311341938,"particle":"pm_10_0","value":18,"max_value":62},{"ts":1608311744202,"particle":"pm_10_0","value":17,"max_value":62},{"ts":1608312146123,"particle":"pm_10_0","value":18,"max_value":62},{"ts":1608312548700,"particle":"pm_10_0","value":18,"max_value":62},{"ts":1608312952492,"particle":"pm_10_0","value":14,"max_value":62},{"ts":1608313354852,"particle":"pm_10_0","value":15,"max_value":62},{"ts":1608313757755,"particle":"pm_10_0","value":17,"max_value":62},{"ts":1608314161659,"particle":"pm_10_0","value":14,"max_value":62},{"ts":1608314563974,"particle":"pm_10_0","value":14,"max_value":62},{"ts":1608314965780,"particle":"pm_10_0","value":12,"max_value":62},{"ts":1608315369314,"particle":"pm_10_0","value":11,"max_value":62},{"ts":1608315770059,"particle":"pm_10_0","value":11,"max_value":62},{"ts":1608316171076,"particle":"pm_10_0","value":11,"max_value":62},{"ts":1608316572092,"particle":"pm_10_0","value":11,"max_value":62},{"ts":1608316971870,"particle":"pm_10_0","value":8,"max_value":62},{"ts":1608317372873,"particle":"pm_10_0","value":8,"max_value":62},{"ts":1608317775734,"particle":"pm_10_0","value":10,"max_value":62},{"ts":1608318177164,"particle":"pm_10_0","value":8,"max_value":62},{"ts":1608318578611,"particle":"pm_10_0","value":9,"max_value":62},{"ts":1608318981514,"particle":"pm_10_0","value":10,"max_value":62},{"ts":1608319383061,"particle":"pm_10_0","value":10,"max_value":62},{"ts":1608319784476,"particle":"pm_10_0","value":10,"max_value":62},{"ts":1608320186378,"particle":"pm_10_0","value":8,"max_value":62},{"ts":1608320589928,"particle":"pm_10_0","value":11,"max_value":62},{"ts":1608320995494,"particle":"pm_10_0","value":12,"max_value":62},{"ts":1608321397223,"particle":"pm_10_0","value":9,"max_value":62},{"ts":1608321799244,"particle":"pm_10_0","value":10,"max_value":62},{"ts":1608322201276,"particle":"pm_10_0","value":11,"max_value":62},{"ts":1608322603388,"particle":"pm_10_0","value":10,"max_value":62},{"ts":1608323005801,"particle":"pm_10_0","value":13,"max_value":62},{"ts":1608323407962,"particle":"pm_10_0","value":12,"max_value":62},{"ts":1608323809705,"particle":"pm_10_0","value":13,"max_value":62},{"ts":1608324211480,"particle":"pm_10_0","value":12,"max_value":62},{"ts":1608324613382,"particle":"pm_10_0","value":12,"max_value":62},{"ts":1608325015664,"particle":"pm_10_0","value":15,"max_value":62},{"ts":1608325418031,"particle":"pm_10_0","value":18,"max_value":62},{"ts":1608325818847,"particle":"pm_10_0","value":15,"max_value":62},{"ts":1608326222452,"particle":"pm_10_0","value":16,"max_value":62},{"ts":1608326623799,"particle":"pm_10_0","value":14,"max_value":62},{"ts":1608327025283,"particle":"pm_10_0","value":14,"max_value":62},{"ts":1608327426380,"particle":"pm_10_0","value":13,"max_value":62},{"ts":1608327828286,"particle":"pm_10_0","value":14,"max_value":62},{"ts":1608328230185,"particle":"pm_10_0","value":16,"max_value":62},{"ts":1608328631922,"particle":"pm_10_0","value":12,"max_value":62},{"ts":1608329033847,"particle":"pm_10_0","value":17,"max_value":62},{"ts":1608329436550,"particle":"pm_10_0","value":18,"max_value":62},{"ts":1608329839483,"particle":"pm_10_0","value":15,"max_value":62},{"ts":1608330241713,"particle":"pm_10_0","value":15,"max_value":62},{"ts":1608330643457,"particle":"pm_10_0","value":16,"max_value":62},{"ts":1608331045411,"particle":"pm_10_0","value":15,"max_value":62},{"ts":1608331447549,"particle":"pm_10_0","value":15,"max_value":62},{"ts":1608331849316,"particle":"pm_10_0","value":13,"max_value":62},{"ts":1608332252470,"particle":"pm_10_0","value":15,"max_value":62},{"ts":1608332654791,"particle":"pm_10_0","value":13,"max_value":62},{"ts":1608333056444,"particle":"pm_10_0","value":13,"max_value":62},{"ts":1608333458073,"particle":"pm_10_0","value":11,"max_value":62},{"ts":1608333861384,"particle":"pm_10_0","value":13,"max_value":62},{"ts":1608334262811,"particle":"pm_10_0","value":12,"max_value":62},{"ts":1608334666153,"particle":"pm_10_0","value":12,"max_value":62},{"ts":1608335067772,"particle":"pm_10_0","value":11,"max_value":62},{"ts":1608335469157,"particle":"pm_10_0","value":11,"max_value":62},{"ts":1608335869903,"particle":"pm_10_0","value":11,"max_value":62},{"ts":1608336270931,"particle":"pm_10_0","value":10,"max_value":62},{"ts":1608336672181,"particle":"pm_10_0","value":10,"max_value":62},{"ts":1608337074385,"particle":"pm_10_0","value":9,"max_value":62},{"ts":1608337475858,"particle":"pm_10_0","value":11,"max_value":62},{"ts":1608337876914,"particle":"pm_10_0","value":9,"max_value":62},{"ts":1608338278053,"particle":"pm_10_0","value":11,"max_value":62},{"ts":1608338679264,"particle":"pm_10_0","value":10,"max_value":62},{"ts":1608339082391,"particle":"pm_10_0","value":11,"max_value":62},{"ts":1608339483849,"particle":"pm_10_0","value":11,"max_value":62},{"ts":1608339885186,"particle":"pm_10_0","value":10,"max_value":62},{"ts":1608340286691,"particle":"pm_10_0","value":10,"max_value":62},{"ts":1608340688099,"particle":"pm_10_0","value":9,"max_value":62},{"ts":1608341089463,"particle":"pm_10_0","value":9,"max_value":62},{"ts":1608341491081,"particle":"pm_10_0","value":9,"max_value":62},{"ts":1608341892868,"particle":"pm_10_0","value":8,"max_value":62},{"ts":1608342295392,"particle":"pm_10_0","value":8,"max_value":62},{"ts":1608342697171,"particle":"pm_10_0","value":8,"max_value":62},{"ts":1608343098743,"particle":"pm_10_0","value":7,"max_value":62},{"ts":1608343500631,"particle":"pm_10_0","value":10,"max_value":62},{"ts":1608343902424,"particle":"pm_10_0","value":8,"max_value":62},{"ts":1608344305742,"particle":"pm_10_0","value":7,"max_value":62},{"ts":1608344707351,"particle":"pm_10_0","value":6,"max_value":62},{"ts":1608345108894,"particle":"pm_10_0","value":7,"max_value":62},{"ts":1608345510684,"particle":"pm_10_0","value":8,"max_value":62},{"ts":1608345911377,"particle":"pm_10_0","value":8,"max_value":62},{"ts":1608346312047,"particle":"pm_10_0","value":6,"max_value":62},{"ts":1608346714527,"particle":"pm_10_0","value":7,"max_value":62},{"ts":1608347116868,"particle":"pm_10_0","value":9,"max_value":62},{"ts":1608347517862,"particle":"pm_10_0","value":7,"max_value":62},{"ts":1608347918884,"particle":"pm_10_0","value":8,"max_value":62},{"ts":1608348320220,"particle":"pm_10_0","value":7,"max_value":62},{"ts":1608348721333,"particle":"pm_10_0","value":6,"max_value":62},{"ts":1608349123010,"particle":"pm_10_0","value":8,"max_value":62},{"ts":1608349524641,"particle":"pm_10_0","value":9,"max_value":62},{"ts":1608349926765,"particle":"pm_10_0","value":12,"max_value":62},{"ts":1608350329711,"particle":"pm_10_0","value":14,"max_value":62},{"ts":1608350732853,"particle":"pm_10_0","value":18,"max_value":62},{"ts":1608351134325,"particle":"pm_10_0","value":16,"max_value":62},{"ts":1608351535667,"particle":"pm_10_0","value":19,"max_value":62},{"ts":1608351937350,"particle":"pm_10_0","value":21,"max_value":62},{"ts":1608352339199,"particle":"pm_10_0","value":20,"max_value":62},{"ts":1608352742444,"particle":"pm_10_0","value":26,"max_value":62},{"ts":1608353144829,"particle":"pm_10_0","value":25,"max_value":62},{"ts":1608353548962,"particle":"pm_10_0","value":26,"max_value":62},{"ts":1608353951652,"particle":"pm_10_0","value":26,"max_value":62},{"ts":1608354354203,"particle":"pm_10_0","value":25,"max_value":62},{"ts":1608354757121,"particle":"pm_10_0","value":24,"max_value":62},{"ts":1608355159324,"particle":"pm_10_0","value":24,"max_value":62},{"ts":1608355562276,"particle":"pm_10_0","value":21,"max_value":62},{"ts":1608355964288,"particle":"pm_10_0","value":23,"max_value":62},{"ts":1608356367413,"particle":"pm_10_0","value":26,"max_value":62},{"ts":1608356768737,"particle":"pm_10_0","value":19,"max_value":62},{"ts":1608357172443,"particle":"pm_10_0","value":21,"max_value":62},{"ts":1608357574297,"particle":"pm_10_0","value":20,"max_value":62},{"ts":1608357975420,"particle":"pm_10_0","value":20,"max_value":62},{"ts":1608358377283,"particle":"pm_10_0","value":20,"max_value":62},{"ts":1608358780290,"particle":"pm_10_0","value":23,"max_value":62},{"ts":1608359183602,"particle":"pm_10_0","value":18,"max_value":62},{"ts":1608359586527,"particle":"pm_10_0","value":20,"max_value":62},{"ts":1608359988447,"particle":"pm_10_0","value":18,"max_value":62},{"ts":1608360389989,"particle":"pm_10_0","value":14,"max_value":62},{"ts":1608360794307,"particle":"pm_10_0","value":19,"max_value":62},{"ts":1608361195676,"particle":"pm_10_0","value":13,"max_value":62},{"ts":1608361597477,"particle":"pm_10_0","value":13,"max_value":62},{"ts":1608362000901,"particle":"pm_10_0","value":13,"max_value":62},{"ts":1608362402860,"particle":"pm_10_0","value":11,"max_value":62},{"ts":1608362804391,"particle":"pm_10_0","value":11,"max_value":62},{"ts":1608363206591,"particle":"pm_10_0","value":10,"max_value":62},{"ts":1608363609830,"particle":"pm_10_0","value":10,"max_value":62},{"ts":1608364011330,"particle":"pm_10_0","value":12,"max_value":62},{"ts":1608364415293,"particle":"pm_10_0","value":12,"max_value":62},{"ts":1608364816886,"particle":"pm_10_0","value":11,"max_value":62},{"ts":1608365217515,"particle":"pm_10_0","value":12,"max_value":62},{"ts":1608365618303,"particle":"pm_10_0","value":8,"max_value":62},{"ts":1608366019079,"particle":"pm_10_0","value":10,"max_value":62},{"ts":1608366420054,"particle":"pm_10_0","value":9,"max_value":62},{"ts":1608366821139,"particle":"pm_10_0","value":10,"max_value":62},{"ts":1608367223228,"particle":"pm_10_0","value":11,"max_value":62},{"ts":1608367624472,"particle":"pm_10_0","value":9,"max_value":62},{"ts":1608368025555,"particle":"pm_10_0","value":10,"max_value":62},{"ts":1608368426816,"particle":"pm_10_0","value":8,"max_value":62},{"ts":1608368828082,"particle":"pm_10_0","value":10,"max_value":62},{"ts":1608369229629,"particle":"pm_10_0","value":10,"max_value":62},{"ts":1608369631453,"particle":"pm_10_0","value":9,"max_value":62},{"ts":1608370033011,"particle":"pm_10_0","value":8,"max_value":62},{"ts":1608370434523,"particle":"pm_10_0","value":8,"max_value":62},{"ts":1608370836062,"particle":"pm_10_0","value":6,"max_value":62},{"ts":1608371237658,"particle":"pm_10_0","value":9,"max_value":62},{"ts":1608371639301,"particle":"pm_10_0","value":8,"max_value":62},{"ts":1608372040797,"particle":"pm_10_0","value":7,"max_value":62},{"ts":1608372442444,"particle":"pm_10_0","value":6,"max_value":62},{"ts":1608372847352,"particle":"pm_10_0","value":6,"max_value":62},{"ts":1608373249083,"particle":"pm_10_0","value":10,"max_value":62},{"ts":1608373651182,"particle":"pm_10_0","value":11,"max_value":62},{"ts":1608374052854,"particle":"pm_10_0","value":7,"max_value":62},{"ts":1608374454640,"particle":"pm_10_0","value":6,"max_value":62},{"ts":1608374855204,"particle":"pm_10_0","value":7,"max_value":62},{"ts":1608375255786,"particle":"pm_10_0","value":7,"max_value":62},{"ts":1608375656705,"particle":"pm_10_0","value":5,"max_value":62},{"ts":1608376057448,"particle":"pm_10_0","value":7,"max_value":62},{"ts":1608376458432,"particle":"pm_10_0","value":6,"max_value":62},{"ts":1608376859383,"particle":"pm_10_0","value":8,"max_value":62},{"ts":1608377260309,"particle":"pm_10_0","value":7,"max_value":62},{"ts":1608377661375,"particle":"pm_10_0","value":5,"max_value":62},{"ts":1608378062387,"particle":"pm_10_0","value":5,"max_value":62},{"ts":1608378463675,"particle":"pm_10_0","value":6,"max_value":62},{"ts":1608378864738,"particle":"pm_10_0","value":6,"max_value":62},{"ts":1608379267590,"particle":"pm_10_0","value":6,"max_value":62},{"ts":1608379668737,"particle":"pm_10_0","value":5,"max_value":62},{"ts":1608380070201,"particle":"pm_10_0","value":6,"max_value":62},{"ts":1608207649154,"particle":"pm_1_0","value":10,"max_value":62},{"ts":1608208050722,"particle":"pm_1_0","value":9,"max_value":62},{"ts":1608208452214,"particle":"pm_1_0","value":9,"max_value":62},{"ts":1608208853684,"particle":"pm_1_0","value":8,"max_value":62},{"ts":1608209255373,"particle":"pm_1_0","value":8,"max_value":62},{"ts":1608209656386,"particle":"pm_1_0","value":8,"max_value":62},{"ts":1608210057540,"particle":"pm_1_0","value":8,"max_value":62},{"ts":1608210458804,"particle":"pm_1_0","value":7,"max_value":62},{"ts":1608210861477,"particle":"pm_1_0","value":6,"max_value":62},{"ts":1608211264801,"particle":"pm_1_0","value":6,"max_value":62},{"ts":1608211666302,"particle":"pm_1_0","value":7,"max_value":62},{"ts":1608212068171,"particle":"pm_1_0","value":7,"max_value":62},{"ts":1608212470325,"particle":"pm_1_0","value":8,"max_value":62},{"ts":1608212872959,"particle":"pm_1_0","value":7,"max_value":62},{"ts":1608213275632,"particle":"pm_1_0","value":7,"max_value":62},{"ts":1608213677154,"particle":"pm_1_0","value":6,"max_value":62},{"ts":1608214079410,"particle":"pm_1_0","value":6,"max_value":62},{"ts":1608214481691,"particle":"pm_1_0","value":6,"max_value":62},{"ts":1608214884340,"particle":"pm_1_0","value":5,"max_value":62},{"ts":1608215286540,"particle":"pm_1_0","value":4,"max_value":62},{"ts":1608215688941,"particle":"pm_1_0","value":5,"max_value":62},{"ts":1608216092745,"particle":"pm_1_0","value":5,"max_value":62},{"ts":1608216494341,"particle":"pm_1_0","value":5,"max_value":62},{"ts":1608216895610,"particle":"pm_1_0","value":5,"max_value":62},{"ts":1608217296428,"particle":"pm_1_0","value":4,"max_value":62},{"ts":1608217697923,"particle":"pm_1_0","value":5,"max_value":62},{"ts":1608218099203,"particle":"pm_1_0","value":5,"max_value":62},{"ts":1608218500536,"particle":"pm_1_0","value":4,"max_value":62},{"ts":1608218901665,"particle":"pm_1_0","value":4,"max_value":62},{"ts":1608219304367,"particle":"pm_1_0","value":3,"max_value":62},{"ts":1608219705412,"particle":"pm_1_0","value":3,"max_value":62},{"ts":1608220106675,"particle":"pm_1_0","value":3,"max_value":62},{"ts":1608220508133,"particle":"pm_1_0","value":3,"max_value":62},{"ts":1608220909537,"particle":"pm_1_0","value":3,"max_value":62},{"ts":1608221311403,"particle":"pm_1_0","value":3,"max_value":62},{"ts":1608221714103,"particle":"pm_1_0","value":3,"max_value":62},{"ts":1608222114857,"particle":"pm_1_0","value":3,"max_value":62},{"ts":1608222516589,"particle":"pm_1_0","value":3,"max_value":62},{"ts":1608222918243,"particle":"pm_1_0","value":3,"max_value":62},{"ts":1608223320052,"particle":"pm_1_0","value":4,"max_value":62},{"ts":1608223721842,"particle":"pm_1_0","value":4,"max_value":62},{"ts":1608224123580,"particle":"pm_1_0","value":3,"max_value":62},{"ts":1608224525231,"particle":"pm_1_0","value":3,"max_value":62},{"ts":1608224928563,"particle":"pm_1_0","value":3,"max_value":62},{"ts":1608225330411,"particle":"pm_1_0","value":3,"max_value":62},{"ts":1608225732511,"particle":"pm_1_0","value":4,"max_value":62},{"ts":1608226134571,"particle":"pm_1_0","value":4,"max_value":62},{"ts":1608226535370,"particle":"pm_1_0","value":4,"max_value":62},{"ts":1608226936238,"particle":"pm_1_0","value":3,"max_value":62},{"ts":1608227337675,"particle":"pm_1_0","value":3,"max_value":62},{"ts":1608227738603,"particle":"pm_1_0","value":3,"max_value":62},{"ts":1608228139548,"particle":"pm_1_0","value":3,"max_value":62},{"ts":1608228542663,"particle":"pm_1_0","value":3,"max_value":62},{"ts":1608228944051,"particle":"pm_1_0","value":4,"max_value":62},{"ts":1608229346775,"particle":"pm_1_0","value":4,"max_value":62},{"ts":1608229747957,"particle":"pm_1_0","value":5,"max_value":62},{"ts":1608230149223,"particle":"pm_1_0","value":5,"max_value":62},{"ts":1608230550664,"particle":"pm_1_0","value":5,"max_value":62},{"ts":1608230953076,"particle":"pm_1_0","value":5,"max_value":62},{"ts":1608231354555,"particle":"pm_1_0","value":5,"max_value":62},{"ts":1608231755959,"particle":"pm_1_0","value":6,"max_value":62},{"ts":1608232158768,"particle":"pm_1_0","value":7,"max_value":62},{"ts":1608232560989,"particle":"pm_1_0","value":6,"max_value":62},{"ts":1608232964122,"particle":"pm_1_0","value":7,"max_value":62},{"ts":1608233365981,"particle":"pm_1_0","value":6,"max_value":62},{"ts":1608233767770,"particle":"pm_1_0","value":6,"max_value":62},{"ts":1608234169570,"particle":"pm_1_0","value":9,"max_value":62},{"ts":1608234573301,"particle":"pm_1_0","value":6,"max_value":62},{"ts":1608234975154,"particle":"pm_1_0","value":6,"max_value":62},{"ts":1608235378401,"particle":"pm_1_0","value":7,"max_value":62},{"ts":1608235780532,"particle":"pm_1_0","value":7,"max_value":62},{"ts":1608236181489,"particle":"pm_1_0","value":7,"max_value":62},{"ts":1608236582895,"particle":"pm_1_0","value":7,"max_value":62},{"ts":1608236983722,"particle":"pm_1_0","value":8,"max_value":62},{"ts":1608237385609,"particle":"pm_1_0","value":7,"max_value":62},{"ts":1608237786477,"particle":"pm_1_0","value":8,"max_value":62},{"ts":1608238187538,"particle":"pm_1_0","value":7,"max_value":62},{"ts":1608238588551,"particle":"pm_1_0","value":8,"max_value":62},{"ts":1608238989580,"particle":"pm_1_0","value":9,"max_value":62},{"ts":1608239394693,"particle":"pm_1_0","value":9,"max_value":62},{"ts":1608239796393,"particle":"pm_1_0","value":10,"max_value":62},{"ts":1608240198518,"particle":"pm_1_0","value":8,"max_value":62},{"ts":1608240600099,"particle":"pm_1_0","value":8,"max_value":62},{"ts":1608241001429,"particle":"pm_1_0","value":7,"max_value":62},{"ts":1608241403217,"particle":"pm_1_0","value":9,"max_value":62},{"ts":1608241805228,"particle":"pm_1_0","value":8,"max_value":62},{"ts":1608242207378,"particle":"pm_1_0","value":8,"max_value":62},{"ts":1608242609621,"particle":"pm_1_0","value":7,"max_value":62},{"ts":1608243011452,"particle":"pm_1_0","value":8,"max_value":62},{"ts":1608243413007,"particle":"pm_1_0","value":7,"max_value":62},{"ts":1608243815064,"particle":"pm_1_0","value":8,"max_value":62},{"ts":1608244216634,"particle":"pm_1_0","value":8,"max_value":62},{"ts":1608244618283,"particle":"pm_1_0","value":8,"max_value":62},{"ts":1608245019992,"particle":"pm_1_0","value":7,"max_value":62},{"ts":1608245421790,"particle":"pm_1_0","value":6,"max_value":62},{"ts":1608245823381,"particle":"pm_1_0","value":6,"max_value":62},{"ts":1608246224892,"particle":"pm_1_0","value":7,"max_value":62},{"ts":1608246625678,"particle":"pm_1_0","value":6,"max_value":62},{"ts":1608247028517,"particle":"pm_1_0","value":7,"max_value":62},{"ts":1608247429871,"particle":"pm_1_0","value":6,"max_value":62},{"ts":1608247832873,"particle":"pm_1_0","value":7,"max_value":62},{"ts":1608248233859,"particle":"pm_1_0","value":6,"max_value":62},{"ts":1608248635074,"particle":"pm_1_0","value":7,"max_value":62},{"ts":1608249036619,"particle":"pm_1_0","value":7,"max_value":62},{"ts":1608249844695,"particle":"pm_1_0","value":7,"max_value":62},{"ts":1608250245776,"particle":"pm_1_0","value":5,"max_value":62},{"ts":1608250647507,"particle":"pm_1_0","value":5,"max_value":62},{"ts":1608251049128,"particle":"pm_1_0","value":6,"max_value":62},{"ts":1608251451016,"particle":"pm_1_0","value":6,"max_value":62},{"ts":1608251852590,"particle":"pm_1_0","value":6,"max_value":62},{"ts":1608252254880,"particle":"pm_1_0","value":5,"max_value":62},{"ts":1608252656441,"particle":"pm_1_0","value":5,"max_value":62},{"ts":1608253057967,"particle":"pm_1_0","value":5,"max_value":62},{"ts":1608253460941,"particle":"pm_1_0","value":6,"max_value":62},{"ts":1608253862834,"particle":"pm_1_0","value":9,"max_value":62},{"ts":1608254264523,"particle":"pm_1_0","value":6,"max_value":62},{"ts":1608254666050,"particle":"pm_1_0","value":7,"max_value":62},{"ts":1608255067832,"particle":"pm_1_0","value":5,"max_value":62},{"ts":1608255470051,"particle":"pm_1_0","value":6,"max_value":62},{"ts":1608255874153,"particle":"pm_1_0","value":6,"max_value":62},{"ts":1608256276210,"particle":"pm_1_0","value":5,"max_value":62},{"ts":1608256677274,"particle":"pm_1_0","value":5,"max_value":62},{"ts":1608257078603,"particle":"pm_1_0","value":5,"max_value":62},{"ts":1608257481252,"particle":"pm_1_0","value":5,"max_value":62},{"ts":1608257883857,"particle":"pm_1_0","value":5,"max_value":62},{"ts":1608258285009,"particle":"pm_1_0","value":4,"max_value":62},{"ts":1608258686063,"particle":"pm_1_0","value":6,"max_value":62},{"ts":1608259087133,"particle":"pm_1_0","value":5,"max_value":62},{"ts":1608259488460,"particle":"pm_1_0","value":4,"max_value":62},{"ts":1608259889667,"particle":"pm_1_0","value":4,"max_value":62},{"ts":1608260291078,"particle":"pm_1_0","value":4,"max_value":62},{"ts":1608260693040,"particle":"pm_1_0","value":4,"max_value":62},{"ts":1608261094988,"particle":"pm_1_0","value":4,"max_value":62},{"ts":1608261496568,"particle":"pm_1_0","value":4,"max_value":62},{"ts":1608261898435,"particle":"pm_1_0","value":4,"max_value":62},{"ts":1608262300169,"particle":"pm_1_0","value":4,"max_value":62},{"ts":1608262701938,"particle":"pm_1_0","value":3,"max_value":62},{"ts":1608263105179,"particle":"pm_1_0","value":4,"max_value":62},{"ts":1608263508270,"particle":"pm_1_0","value":4,"max_value":62},{"ts":1608263910108,"particle":"pm_1_0","value":4,"max_value":62},{"ts":1608264311930,"particle":"pm_1_0","value":3,"max_value":62},{"ts":1608264713753,"particle":"pm_1_0","value":3,"max_value":62},{"ts":1608265114653,"particle":"pm_1_0","value":3,"max_value":62},{"ts":1608265516562,"particle":"pm_1_0","value":3,"max_value":62},{"ts":1608265918222,"particle":"pm_1_0","value":3,"max_value":62},{"ts":1608266319068,"particle":"pm_1_0","value":3,"max_value":62},{"ts":1608266719848,"particle":"pm_1_0","value":3,"max_value":62},{"ts":1608267120698,"particle":"pm_1_0","value":2,"max_value":62},{"ts":1608267521929,"particle":"pm_1_0","value":3,"max_value":62},{"ts":1608267922945,"particle":"pm_1_0","value":3,"max_value":62},{"ts":1608268324531,"particle":"pm_1_0","value":3,"max_value":62},{"ts":1608268725602,"particle":"pm_1_0","value":2,"max_value":62},{"ts":1608269126800,"particle":"pm_1_0","value":2,"max_value":62},{"ts":1608269528066,"particle":"pm_1_0","value":2,"max_value":62},{"ts":1608269929292,"particle":"pm_1_0","value":3,"max_value":62},{"ts":1608270332191,"particle":"pm_1_0","value":3,"max_value":62},{"ts":1608270733613,"particle":"pm_1_0","value":2,"max_value":62},{"ts":1608271136572,"particle":"pm_1_0","value":3,"max_value":62},{"ts":1608271537937,"particle":"pm_1_0","value":3,"max_value":62},{"ts":1608271939473,"particle":"pm_1_0","value":2,"max_value":62},{"ts":1608272341101,"particle":"pm_1_0","value":3,"max_value":62},{"ts":1608272742764,"particle":"pm_1_0","value":3,"max_value":62},{"ts":1608273144532,"particle":"pm_1_0","value":2,"max_value":62},{"ts":1608273546285,"particle":"pm_1_0","value":3,"max_value":62},{"ts":1608273948890,"particle":"pm_1_0","value":3,"max_value":62},{"ts":1608274350720,"particle":"pm_1_0","value":2,"max_value":62},{"ts":1608274752491,"particle":"pm_1_0","value":3,"max_value":62},{"ts":1608275154174,"particle":"pm_1_0","value":3,"max_value":62},{"ts":1608275556681,"particle":"pm_1_0","value":2,"max_value":62},{"ts":1608275957605,"particle":"pm_1_0","value":2,"max_value":62},{"ts":1608276358262,"particle":"pm_1_0","value":3,"max_value":62},{"ts":1608276758914,"particle":"pm_1_0","value":3,"max_value":62},{"ts":1608277161116,"particle":"pm_1_0","value":3,"max_value":62},{"ts":1608277562060,"particle":"pm_1_0","value":3,"max_value":62},{"ts":1608277963298,"particle":"pm_1_0","value":4,"max_value":62},{"ts":1608278364342,"particle":"pm_1_0","value":4,"max_value":62},{"ts":1608278765364,"particle":"pm_1_0","value":4,"max_value":62},{"ts":1608279166104,"particle":"pm_1_0","value":3,"max_value":62},{"ts":1608279567390,"particle":"pm_1_0","value":3,"max_value":62},{"ts":1608279970534,"particle":"pm_1_0","value":3,"max_value":62},{"ts":1608280372087,"particle":"pm_1_0","value":3,"max_value":62},{"ts":1608280773717,"particle":"pm_1_0","value":3,"max_value":62},{"ts":1608281175989,"particle":"pm_1_0","value":3,"max_value":62},{"ts":1608281577632,"particle":"pm_1_0","value":3,"max_value":62},{"ts":1608281980919,"particle":"pm_1_0","value":4,"max_value":62},{"ts":1608282384594,"particle":"pm_1_0","value":3,"max_value":62},{"ts":1608282787983,"particle":"pm_1_0","value":4,"max_value":62},{"ts":1608283189940,"particle":"pm_1_0","value":4,"max_value":62},{"ts":1608283591882,"particle":"pm_1_0","value":3,"max_value":62},{"ts":1608283997911,"particle":"pm_1_0","value":4,"max_value":62},{"ts":1608284399632,"particle":"pm_1_0","value":4,"max_value":62},{"ts":1608284801640,"particle":"pm_1_0","value":4,"max_value":62},{"ts":1608285203922,"particle":"pm_1_0","value":3,"max_value":62},{"ts":1608285607982,"particle":"pm_1_0","value":3,"max_value":62},{"ts":1608286010730,"particle":"pm_1_0","value":4,"max_value":62},{"ts":1608286411873,"particle":"pm_1_0","value":3,"max_value":62},{"ts":1608286816519,"particle":"pm_1_0","value":4,"max_value":62},{"ts":1608287217624,"particle":"pm_1_0","value":4,"max_value":62},{"ts":1608287618929,"particle":"pm_1_0","value":4,"max_value":62},{"ts":1608288020104,"particle":"pm_1_0","value":4,"max_value":62},{"ts":1608288421448,"particle":"pm_1_0","value":4,"max_value":62},{"ts":1608288824442,"particle":"pm_1_0","value":3,"max_value":62},{"ts":1608289226023,"particle":"pm_1_0","value":4,"max_value":62},{"ts":1608289627832,"particle":"pm_1_0","value":3,"max_value":62},{"ts":1608290029641,"particle":"pm_1_0","value":4,"max_value":62},{"ts":1608290431469,"particle":"pm_1_0","value":3,"max_value":62},{"ts":1608290833215,"particle":"pm_1_0","value":3,"max_value":62},{"ts":1608291236457,"particle":"pm_1_0","value":4,"max_value":62},{"ts":1608291638073,"particle":"pm_1_0","value":4,"max_value":62},{"ts":1608292040111,"particle":"pm_1_0","value":4,"max_value":62},{"ts":1608292442308,"particle":"pm_1_0","value":3,"max_value":62},{"ts":1608292843950,"particle":"pm_1_0","value":4,"max_value":62},{"ts":1608293245374,"particle":"pm_1_0","value":6,"max_value":62},{"ts":1608293648772,"particle":"pm_1_0","value":5,"max_value":62},{"ts":1608294050572,"particle":"pm_1_0","value":5,"max_value":62},{"ts":1608294452274,"particle":"pm_1_0","value":4,"max_value":62},{"ts":1608294854104,"particle":"pm_1_0","value":4,"max_value":62},{"ts":1608295256392,"particle":"pm_1_0","value":4,"max_value":62},{"ts":1608295658150,"particle":"pm_1_0","value":5,"max_value":62},{"ts":1608296059004,"particle":"pm_1_0","value":4,"max_value":62},{"ts":1608296461327,"particle":"pm_1_0","value":5,"max_value":62},{"ts":1608296862117,"particle":"pm_1_0","value":4,"max_value":62},{"ts":1608297263273,"particle":"pm_1_0","value":5,"max_value":62},{"ts":1608297665525,"particle":"pm_1_0","value":4,"max_value":62},{"ts":1608298065242,"particle":"pm_1_0","value":4,"max_value":62},{"ts":1608298466290,"particle":"pm_1_0","value":3,"max_value":62},{"ts":1608298867254,"particle":"pm_1_0","value":4,"max_value":62},{"ts":1608299268402,"particle":"pm_1_0","value":5,"max_value":62},{"ts":1608299669651,"particle":"pm_1_0","value":5,"max_value":62},{"ts":1608300070738,"particle":"pm_1_0","value":4,"max_value":62},{"ts":1608300472372,"particle":"pm_1_0","value":5,"max_value":62},{"ts":1608300874235,"particle":"pm_1_0","value":5,"max_value":62},{"ts":1608301276494,"particle":"pm_1_0","value":17,"max_value":62},{"ts":1608301679972,"particle":"pm_1_0","value":25,"max_value":62},{"ts":1608302083093,"particle":"pm_1_0","value":23,"max_value":62},{"ts":1608302487862,"particle":"pm_1_0","value":23,"max_value":62},{"ts":1608302890471,"particle":"pm_1_0","value":24,"max_value":62},{"ts":1608303292971,"particle":"pm_1_0","value":25,"max_value":62},{"ts":1608303697014,"particle":"pm_1_0","value":26,"max_value":62},{"ts":1608304099550,"particle":"pm_1_0","value":26,"max_value":62},{"ts":1608304503520,"particle":"pm_1_0","value":26,"max_value":62},{"ts":1608304906244,"particle":"pm_1_0","value":26,"max_value":62},{"ts":1608305309552,"particle":"pm_1_0","value":25,"max_value":62},{"ts":1608305714343,"particle":"pm_1_0","value":25,"max_value":62},{"ts":1608306115248,"particle":"pm_1_0","value":24,"max_value":62},{"ts":1608306516974,"particle":"pm_1_0","value":25,"max_value":62},{"ts":1608306919095,"particle":"pm_1_0","value":24,"max_value":62},{"ts":1608307321820,"particle":"pm_1_0","value":24,"max_value":62},{"ts":1608307724080,"particle":"pm_1_0","value":24,"max_value":62},{"ts":1608308125978,"particle":"pm_1_0","value":22,"max_value":62},{"ts":1608308526909,"particle":"pm_1_0","value":20,"max_value":62},{"ts":1608308930161,"particle":"pm_1_0","value":21,"max_value":62},{"ts":1608309331908,"particle":"pm_1_0","value":19,"max_value":62},{"ts":1608309733873,"particle":"pm_1_0","value":17,"max_value":62},{"ts":1608310136031,"particle":"pm_1_0","value":16,"max_value":62},{"ts":1608310537076,"particle":"pm_1_0","value":15,"max_value":62},{"ts":1608310940707,"particle":"pm_1_0","value":14,"max_value":62},{"ts":1608311341938,"particle":"pm_1_0","value":12,"max_value":62},{"ts":1608311744202,"particle":"pm_1_0","value":10,"max_value":62},{"ts":1608312146123,"particle":"pm_1_0","value":11,"max_value":62},{"ts":1608312548700,"particle":"pm_1_0","value":10,"max_value":62},{"ts":1608312952492,"particle":"pm_1_0","value":10,"max_value":62},{"ts":1608313354852,"particle":"pm_1_0","value":9,"max_value":62},{"ts":1608313757755,"particle":"pm_1_0","value":9,"max_value":62},{"ts":1608314161659,"particle":"pm_1_0","value":8,"max_value":62},{"ts":1608314563974,"particle":"pm_1_0","value":8,"max_value":62},{"ts":1608314965780,"particle":"pm_1_0","value":8,"max_value":62},{"ts":1608315369314,"particle":"pm_1_0","value":7,"max_value":62},{"ts":1608315770059,"particle":"pm_1_0","value":8,"max_value":62},{"ts":1608316171076,"particle":"pm_1_0","value":7,"max_value":62},{"ts":1608316572092,"particle":"pm_1_0","value":7,"max_value":62},{"ts":1608316971870,"particle":"pm_1_0","value":5,"max_value":62},{"ts":1608317372873,"particle":"pm_1_0","value":6,"max_value":62},{"ts":1608317775734,"particle":"pm_1_0","value":6,"max_value":62},{"ts":1608318177164,"particle":"pm_1_0","value":5,"max_value":62},{"ts":1608318578611,"particle":"pm_1_0","value":6,"max_value":62},{"ts":1608318981514,"particle":"pm_1_0","value":6,"max_value":62},{"ts":1608319383061,"particle":"pm_1_0","value":6,"max_value":62},{"ts":1608319784476,"particle":"pm_1_0","value":6,"max_value":62},{"ts":1608320186378,"particle":"pm_1_0","value":6,"max_value":62},{"ts":1608320589928,"particle":"pm_1_0","value":6,"max_value":62},{"ts":1608320995494,"particle":"pm_1_0","value":6,"max_value":62},{"ts":1608321397223,"particle":"pm_1_0","value":6,"max_value":62},{"ts":1608321799244,"particle":"pm_1_0","value":7,"max_value":62},{"ts":1608322201276,"particle":"pm_1_0","value":7,"max_value":62},{"ts":1608322603388,"particle":"pm_1_0","value":6,"max_value":62},{"ts":1608323005801,"particle":"pm_1_0","value":8,"max_value":62},{"ts":1608323407962,"particle":"pm_1_0","value":8,"max_value":62},{"ts":1608323809705,"particle":"pm_1_0","value":8,"max_value":62},{"ts":1608324211480,"particle":"pm_1_0","value":8,"max_value":62},{"ts":1608324613382,"particle":"pm_1_0","value":8,"max_value":62},{"ts":1608325015664,"particle":"pm_1_0","value":9,"max_value":62},{"ts":1608325418031,"particle":"pm_1_0","value":10,"max_value":62},{"ts":1608325818847,"particle":"pm_1_0","value":9,"max_value":62},{"ts":1608326222452,"particle":"pm_1_0","value":8,"max_value":62},{"ts":1608326623799,"particle":"pm_1_0","value":8,"max_value":62},{"ts":1608327025283,"particle":"pm_1_0","value":9,"max_value":62},{"ts":1608327426380,"particle":"pm_1_0","value":8,"max_value":62},{"ts":1608327828286,"particle":"pm_1_0","value":8,"max_value":62},{"ts":1608328230185,"particle":"pm_1_0","value":8,"max_value":62},{"ts":1608328631922,"particle":"pm_1_0","value":8,"max_value":62},{"ts":1608329033847,"particle":"pm_1_0","value":9,"max_value":62},{"ts":1608329436550,"particle":"pm_1_0","value":10,"max_value":62},{"ts":1608329839483,"particle":"pm_1_0","value":9,"max_value":62},{"ts":1608330241713,"particle":"pm_1_0","value":10,"max_value":62},{"ts":1608330643457,"particle":"pm_1_0","value":10,"max_value":62},{"ts":1608331045411,"particle":"pm_1_0","value":9,"max_value":62},{"ts":1608331447549,"particle":"pm_1_0","value":9,"max_value":62},{"ts":1608331849316,"particle":"pm_1_0","value":8,"max_value":62},{"ts":1608332252470,"particle":"pm_1_0","value":9,"max_value":62},{"ts":1608332654791,"particle":"pm_1_0","value":8,"max_value":62},{"ts":1608333056444,"particle":"pm_1_0","value":8,"max_value":62},{"ts":1608333458073,"particle":"pm_1_0","value":7,"max_value":62},{"ts":1608333861384,"particle":"pm_1_0","value":8,"max_value":62},{"ts":1608334262811,"particle":"pm_1_0","value":8,"max_value":62},{"ts":1608334666153,"particle":"pm_1_0","value":8,"max_value":62},{"ts":1608335067772,"particle":"pm_1_0","value":7,"max_value":62},{"ts":1608335469157,"particle":"pm_1_0","value":7,"max_value":62},{"ts":1608335869903,"particle":"pm_1_0","value":7,"max_value":62},{"ts":1608336270931,"particle":"pm_1_0","value":7,"max_value":62},{"ts":1608336672181,"particle":"pm_1_0","value":6,"max_value":62},{"ts":1608337074385,"particle":"pm_1_0","value":7,"max_value":62},{"ts":1608337475858,"particle":"pm_1_0","value":7,"max_value":62},{"ts":1608337876914,"particle":"pm_1_0","value":7,"max_value":62},{"ts":1608338278053,"particle":"pm_1_0","value":7,"max_value":62},{"ts":1608338679264,"particle":"pm_1_0","value":7,"max_value":62},{"ts":1608339082391,"particle":"pm_1_0","value":6,"max_value":62},{"ts":1608339483849,"particle":"pm_1_0","value":7,"max_value":62},{"ts":1608339885186,"particle":"pm_1_0","value":6,"max_value":62},{"ts":1608340286691,"particle":"pm_1_0","value":6,"max_value":62},{"ts":1608340688099,"particle":"pm_1_0","value":7,"max_value":62},{"ts":1608341089463,"particle":"pm_1_0","value":7,"max_value":62},{"ts":1608341491081,"particle":"pm_1_0","value":6,"max_value":62},{"ts":1608341892868,"particle":"pm_1_0","value":6,"max_value":62},{"ts":1608342295392,"particle":"pm_1_0","value":5,"max_value":62},{"ts":1608342697171,"particle":"pm_1_0","value":5,"max_value":62},{"ts":1608343098743,"particle":"pm_1_0","value":5,"max_value":62},{"ts":1608343500631,"particle":"pm_1_0","value":6,"max_value":62},{"ts":1608343902424,"particle":"pm_1_0","value":5,"max_value":62},{"ts":1608344305742,"particle":"pm_1_0","value":5,"max_value":62},{"ts":1608344707351,"particle":"pm_1_0","value":4,"max_value":62},{"ts":1608345108894,"particle":"pm_1_0","value":5,"max_value":62},{"ts":1608345510684,"particle":"pm_1_0","value":6,"max_value":62},{"ts":1608345911377,"particle":"pm_1_0","value":5,"max_value":62},{"ts":1608346312047,"particle":"pm_1_0","value":5,"max_value":62},{"ts":1608346714527,"particle":"pm_1_0","value":5,"max_value":62},{"ts":1608347116868,"particle":"pm_1_0","value":5,"max_value":62},{"ts":1608347517862,"particle":"pm_1_0","value":5,"max_value":62},{"ts":1608347918884,"particle":"pm_1_0","value":5,"max_value":62},{"ts":1608348320220,"particle":"pm_1_0","value":5,"max_value":62},{"ts":1608348721333,"particle":"pm_1_0","value":4,"max_value":62},{"ts":1608349123010,"particle":"pm_1_0","value":5,"max_value":62},{"ts":1608349524641,"particle":"pm_1_0","value":6,"max_value":62},{"ts":1608349926765,"particle":"pm_1_0","value":7,"max_value":62},{"ts":1608350329711,"particle":"pm_1_0","value":8,"max_value":62},{"ts":1608350732853,"particle":"pm_1_0","value":9,"max_value":62},{"ts":1608351134325,"particle":"pm_1_0","value":10,"max_value":62},{"ts":1608351535667,"particle":"pm_1_0","value":12,"max_value":62},{"ts":1608351937350,"particle":"pm_1_0","value":13,"max_value":62},{"ts":1608352339199,"particle":"pm_1_0","value":13,"max_value":62},{"ts":1608352742444,"particle":"pm_1_0","value":14,"max_value":62},{"ts":1608353144829,"particle":"pm_1_0","value":14,"max_value":62},{"ts":1608353548962,"particle":"pm_1_0","value":13,"max_value":62},{"ts":1608353951652,"particle":"pm_1_0","value":14,"max_value":62},{"ts":1608354354203,"particle":"pm_1_0","value":15,"max_value":62},{"ts":1608354757121,"particle":"pm_1_0","value":14,"max_value":62},{"ts":1608355159324,"particle":"pm_1_0","value":13,"max_value":62},{"ts":1608355562276,"particle":"pm_1_0","value":12,"max_value":62},{"ts":1608355964288,"particle":"pm_1_0","value":13,"max_value":62},{"ts":1608356367413,"particle":"pm_1_0","value":13,"max_value":62},{"ts":1608356768737,"particle":"pm_1_0","value":11,"max_value":62},{"ts":1608357172443,"particle":"pm_1_0","value":12,"max_value":62},{"ts":1608357574297,"particle":"pm_1_0","value":12,"max_value":62},{"ts":1608357975420,"particle":"pm_1_0","value":11,"max_value":62},{"ts":1608358377283,"particle":"pm_1_0","value":11,"max_value":62},{"ts":1608358780290,"particle":"pm_1_0","value":11,"max_value":62},{"ts":1608359183602,"particle":"pm_1_0","value":11,"max_value":62},{"ts":1608359586527,"particle":"pm_1_0","value":10,"max_value":62},{"ts":1608359988447,"particle":"pm_1_0","value":9,"max_value":62},{"ts":1608360389989,"particle":"pm_1_0","value":8,"max_value":62},{"ts":1608360794307,"particle":"pm_1_0","value":10,"max_value":62},{"ts":1608361195676,"particle":"pm_1_0","value":8,"max_value":62},{"ts":1608361597477,"particle":"pm_1_0","value":7,"max_value":62},{"ts":1608362000901,"particle":"pm_1_0","value":8,"max_value":62},{"ts":1608362402860,"particle":"pm_1_0","value":7,"max_value":62},{"ts":1608362804391,"particle":"pm_1_0","value":6,"max_value":62},{"ts":1608363206591,"particle":"pm_1_0","value":6,"max_value":62},{"ts":1608363609830,"particle":"pm_1_0","value":6,"max_value":62},{"ts":1608364011330,"particle":"pm_1_0","value":6,"max_value":62},{"ts":1608364415293,"particle":"pm_1_0","value":6,"max_value":62},{"ts":1608364816886,"particle":"pm_1_0","value":7,"max_value":62},{"ts":1608365217515,"particle":"pm_1_0","value":6,"max_value":62},{"ts":1608365618303,"particle":"pm_1_0","value":5,"max_value":62},{"ts":1608366019079,"particle":"pm_1_0","value":6,"max_value":62},{"ts":1608366420054,"particle":"pm_1_0","value":4,"max_value":62},{"ts":1608366821139,"particle":"pm_1_0","value":5,"max_value":62},{"ts":1608367223228,"particle":"pm_1_0","value":5,"max_value":62},{"ts":1608367624472,"particle":"pm_1_0","value":5,"max_value":62},{"ts":1608368025555,"particle":"pm_1_0","value":5,"max_value":62},{"ts":1608368426816,"particle":"pm_1_0","value":5,"max_value":62},{"ts":1608368828082,"particle":"pm_1_0","value":5,"max_value":62},{"ts":1608369229629,"particle":"pm_1_0","value":5,"max_value":62},{"ts":1608369631453,"particle":"pm_1_0","value":5,"max_value":62},{"ts":1608370033011,"particle":"pm_1_0","value":5,"max_value":62},{"ts":1608370434523,"particle":"pm_1_0","value":5,"max_value":62},{"ts":1608370836062,"particle":"pm_1_0","value":4,"max_value":62},{"ts":1608371237658,"particle":"pm_1_0","value":5,"max_value":62},{"ts":1608371639301,"particle":"pm_1_0","value":5,"max_value":62},{"ts":1608372040797,"particle":"pm_1_0","value":4,"max_value":62},{"ts":1608372442444,"particle":"pm_1_0","value":4,"max_value":62},{"ts":1608372847352,"particle":"pm_1_0","value":4,"max_value":62},{"ts":1608373249083,"particle":"pm_1_0","value":6,"max_value":62},{"ts":1608373651182,"particle":"pm_1_0","value":6,"max_value":62},{"ts":1608374052854,"particle":"pm_1_0","value":5,"max_value":62},{"ts":1608374454640,"particle":"pm_1_0","value":4,"max_value":62},{"ts":1608374855204,"particle":"pm_1_0","value":4,"max_value":62},{"ts":1608375255786,"particle":"pm_1_0","value":4,"max_value":62},{"ts":1608375656705,"particle":"pm_1_0","value":4,"max_value":62},{"ts":1608376057448,"particle":"pm_1_0","value":4,"max_value":62},{"ts":1608376458432,"particle":"pm_1_0","value":4,"max_value":62},{"ts":1608376859383,"particle":"pm_1_0","value":4,"max_value":62},{"ts":1608377260309,"particle":"pm_1_0","value":4,"max_value":62},{"ts":1608377661375,"particle":"pm_1_0","value":3,"max_value":62},{"ts":1608378062387,"particle":"pm_1_0","value":4,"max_value":62},{"ts":1608378463675,"particle":"pm_1_0","value":3,"max_value":62},{"ts":1608378864738,"particle":"pm_1_0","value":4,"max_value":62},{"ts":1608379267590,"particle":"pm_1_0","value":3,"max_value":62},{"ts":1608379668737,"particle":"pm_1_0","value":4,"max_value":62},{"ts":1608380070201,"particle":"pm_1_0","value":3,"max_value":62},{"ts":1608207649154,"particle":"pm_2_5","value":18,"max_value":62},{"ts":1608208050722,"particle":"pm_2_5","value":16,"max_value":62},{"ts":1608208452214,"particle":"pm_2_5","value":14,"max_value":62},{"ts":1608208853684,"particle":"pm_2_5","value":15,"max_value":62},{"ts":1608209255373,"particle":"pm_2_5","value":15,"max_value":62},{"ts":1608209656386,"particle":"pm_2_5","value":13,"max_value":62},{"ts":1608210057540,"particle":"pm_2_5","value":11,"max_value":62},{"ts":1608210458804,"particle":"pm_2_5","value":11,"max_value":62},{"ts":1608210861477,"particle":"pm_2_5","value":11,"max_value":62},{"ts":1608211264801,"particle":"pm_2_5","value":12,"max_value":62},{"ts":1608211666302,"particle":"pm_2_5","value":12,"max_value":62},{"ts":1608212068171,"particle":"pm_2_5","value":12,"max_value":62},{"ts":1608212470325,"particle":"pm_2_5","value":13,"max_value":62},{"ts":1608212872959,"particle":"pm_2_5","value":13,"max_value":62},{"ts":1608213275632,"particle":"pm_2_5","value":14,"max_value":62},{"ts":1608213677154,"particle":"pm_2_5","value":9,"max_value":62},{"ts":1608214079410,"particle":"pm_2_5","value":9,"max_value":62},{"ts":1608214481691,"particle":"pm_2_5","value":10,"max_value":62},{"ts":1608214884340,"particle":"pm_2_5","value":9,"max_value":62},{"ts":1608215286540,"particle":"pm_2_5","value":9,"max_value":62},{"ts":1608215688941,"particle":"pm_2_5","value":9,"max_value":62},{"ts":1608216092745,"particle":"pm_2_5","value":9,"max_value":62},{"ts":1608216494341,"particle":"pm_2_5","value":7,"max_value":62},{"ts":1608216895610,"particle":"pm_2_5","value":8,"max_value":62},{"ts":1608217296428,"particle":"pm_2_5","value":6,"max_value":62},{"ts":1608217697923,"particle":"pm_2_5","value":9,"max_value":62},{"ts":1608218099203,"particle":"pm_2_5","value":7,"max_value":62},{"ts":1608218500536,"particle":"pm_2_5","value":7,"max_value":62},{"ts":1608218901665,"particle":"pm_2_5","value":6,"max_value":62},{"ts":1608219304367,"particle":"pm_2_5","value":5,"max_value":62},{"ts":1608219705412,"particle":"pm_2_5","value":6,"max_value":62},{"ts":1608220106675,"particle":"pm_2_5","value":5,"max_value":62},{"ts":1608220508133,"particle":"pm_2_5","value":5,"max_value":62},{"ts":1608220909537,"particle":"pm_2_5","value":4,"max_value":62},{"ts":1608221311403,"particle":"pm_2_5","value":5,"max_value":62},{"ts":1608221714103,"particle":"pm_2_5","value":4,"max_value":62},{"ts":1608222114857,"particle":"pm_2_5","value":4,"max_value":62},{"ts":1608222516589,"particle":"pm_2_5","value":4,"max_value":62},{"ts":1608222918243,"particle":"pm_2_5","value":5,"max_value":62},{"ts":1608223320052,"particle":"pm_2_5","value":5,"max_value":62},{"ts":1608223721842,"particle":"pm_2_5","value":5,"max_value":62},{"ts":1608224123580,"particle":"pm_2_5","value":6,"max_value":62},{"ts":1608224525231,"particle":"pm_2_5","value":5,"max_value":62},{"ts":1608224928563,"particle":"pm_2_5","value":4,"max_value":62},{"ts":1608225330411,"particle":"pm_2_5","value":5,"max_value":62},{"ts":1608225732511,"particle":"pm_2_5","value":5,"max_value":62},{"ts":1608226134571,"particle":"pm_2_5","value":5,"max_value":62},{"ts":1608226535370,"particle":"pm_2_5","value":5,"max_value":62},{"ts":1608226936238,"particle":"pm_2_5","value":5,"max_value":62},{"ts":1608227337675,"particle":"pm_2_5","value":6,"max_value":62},{"ts":1608227738603,"particle":"pm_2_5","value":5,"max_value":62},{"ts":1608228139548,"particle":"pm_2_5","value":7,"max_value":62},{"ts":1608228542663,"particle":"pm_2_5","value":5,"max_value":62},{"ts":1608228944051,"particle":"pm_2_5","value":7,"max_value":62},{"ts":1608229346775,"particle":"pm_2_5","value":6,"max_value":62},{"ts":1608229747957,"particle":"pm_2_5","value":7,"max_value":62},{"ts":1608230149223,"particle":"pm_2_5","value":8,"max_value":62},{"ts":1608230550664,"particle":"pm_2_5","value":7,"max_value":62},{"ts":1608230953076,"particle":"pm_2_5","value":8,"max_value":62},{"ts":1608231354555,"particle":"pm_2_5","value":8,"max_value":62},{"ts":1608231755959,"particle":"pm_2_5","value":10,"max_value":62},{"ts":1608232158768,"particle":"pm_2_5","value":14,"max_value":62},{"ts":1608232560989,"particle":"pm_2_5","value":11,"max_value":62},{"ts":1608232964122,"particle":"pm_2_5","value":10,"max_value":62},{"ts":1608233365981,"particle":"pm_2_5","value":9,"max_value":62},{"ts":1608233767770,"particle":"pm_2_5","value":8,"max_value":62},{"ts":1608234169570,"particle":"pm_2_5","value":15,"max_value":62},{"ts":1608234573301,"particle":"pm_2_5","value":11,"max_value":62},{"ts":1608234975154,"particle":"pm_2_5","value":10,"max_value":62},{"ts":1608235378401,"particle":"pm_2_5","value":10,"max_value":62},{"ts":1608235780532,"particle":"pm_2_5","value":12,"max_value":62},{"ts":1608236181489,"particle":"pm_2_5","value":11,"max_value":62},{"ts":1608236582895,"particle":"pm_2_5","value":11,"max_value":62},{"ts":1608236983722,"particle":"pm_2_5","value":11,"max_value":62},{"ts":1608237385609,"particle":"pm_2_5","value":13,"max_value":62},{"ts":1608237786477,"particle":"pm_2_5","value":11,"max_value":62},{"ts":1608238187538,"particle":"pm_2_5","value":11,"max_value":62},{"ts":1608238588551,"particle":"pm_2_5","value":12,"max_value":62},{"ts":1608238989580,"particle":"pm_2_5","value":13,"max_value":62},{"ts":1608239394693,"particle":"pm_2_5","value":13,"max_value":62},{"ts":1608239796393,"particle":"pm_2_5","value":17,"max_value":62},{"ts":1608240198518,"particle":"pm_2_5","value":13,"max_value":62},{"ts":1608240600099,"particle":"pm_2_5","value":12,"max_value":62},{"ts":1608241001429,"particle":"pm_2_5","value":11,"max_value":62},{"ts":1608241403217,"particle":"pm_2_5","value":13,"max_value":62},{"ts":1608241805228,"particle":"pm_2_5","value":11,"max_value":62},{"ts":1608242207378,"particle":"pm_2_5","value":13,"max_value":62},{"ts":1608242609621,"particle":"pm_2_5","value":14,"max_value":62},{"ts":1608243011452,"particle":"pm_2_5","value":11,"max_value":62},{"ts":1608243413007,"particle":"pm_2_5","value":11,"max_value":62},{"ts":1608243815064,"particle":"pm_2_5","value":12,"max_value":62},{"ts":1608244216634,"particle":"pm_2_5","value":12,"max_value":62},{"ts":1608244618283,"particle":"pm_2_5","value":11,"max_value":62},{"ts":1608245019992,"particle":"pm_2_5","value":11,"max_value":62},{"ts":1608245421790,"particle":"pm_2_5","value":10,"max_value":62},{"ts":1608245823381,"particle":"pm_2_5","value":9,"max_value":62},{"ts":1608246224892,"particle":"pm_2_5","value":10,"max_value":62},{"ts":1608246625678,"particle":"pm_2_5","value":9,"max_value":62},{"ts":1608247028517,"particle":"pm_2_5","value":12,"max_value":62},{"ts":1608247429871,"particle":"pm_2_5","value":10,"max_value":62},{"ts":1608247832873,"particle":"pm_2_5","value":12,"max_value":62},{"ts":1608248233859,"particle":"pm_2_5","value":10,"max_value":62},{"ts":1608248635074,"particle":"pm_2_5","value":9,"max_value":62},{"ts":1608249036619,"particle":"pm_2_5","value":10,"max_value":62},{"ts":1608249844695,"particle":"pm_2_5","value":12,"max_value":62},{"ts":1608250245776,"particle":"pm_2_5","value":10,"max_value":62},{"ts":1608250647507,"particle":"pm_2_5","value":9,"max_value":62},{"ts":1608251049128,"particle":"pm_2_5","value":9,"max_value":62},{"ts":1608251451016,"particle":"pm_2_5","value":10,"max_value":62},{"ts":1608251852590,"particle":"pm_2_5","value":9,"max_value":62},{"ts":1608252254880,"particle":"pm_2_5","value":10,"max_value":62},{"ts":1608252656441,"particle":"pm_2_5","value":8,"max_value":62},{"ts":1608253057967,"particle":"pm_2_5","value":7,"max_value":62},{"ts":1608253460941,"particle":"pm_2_5","value":11,"max_value":62},{"ts":1608253862834,"particle":"pm_2_5","value":14,"max_value":62},{"ts":1608254264523,"particle":"pm_2_5","value":11,"max_value":62},{"ts":1608254666050,"particle":"pm_2_5","value":9,"max_value":62},{"ts":1608255067832,"particle":"pm_2_5","value":8,"max_value":62},{"ts":1608255470051,"particle":"pm_2_5","value":10,"max_value":62},{"ts":1608255874153,"particle":"pm_2_5","value":11,"max_value":62},{"ts":1608256276210,"particle":"pm_2_5","value":8,"max_value":62},{"ts":1608256677274,"particle":"pm_2_5","value":9,"max_value":62},{"ts":1608257078603,"particle":"pm_2_5","value":6,"max_value":62},{"ts":1608257481252,"particle":"pm_2_5","value":7,"max_value":62},{"ts":1608257883857,"particle":"pm_2_5","value":8,"max_value":62},{"ts":1608258285009,"particle":"pm_2_5","value":7,"max_value":62},{"ts":1608258686063,"particle":"pm_2_5","value":8,"max_value":62},{"ts":1608259087133,"particle":"pm_2_5","value":8,"max_value":62},{"ts":1608259488460,"particle":"pm_2_5","value":7,"max_value":62},{"ts":1608259889667,"particle":"pm_2_5","value":6,"max_value":62},{"ts":1608260291078,"particle":"pm_2_5","value":6,"max_value":62},{"ts":1608260693040,"particle":"pm_2_5","value":9,"max_value":62},{"ts":1608261094988,"particle":"pm_2_5","value":6,"max_value":62},{"ts":1608261496568,"particle":"pm_2_5","value":7,"max_value":62},{"ts":1608261898435,"particle":"pm_2_5","value":6,"max_value":62},{"ts":1608262300169,"particle":"pm_2_5","value":6,"max_value":62},{"ts":1608262701938,"particle":"pm_2_5","value":6,"max_value":62},{"ts":1608263105179,"particle":"pm_2_5","value":6,"max_value":62},{"ts":1608263508270,"particle":"pm_2_5","value":6,"max_value":62},{"ts":1608263910108,"particle":"pm_2_5","value":6,"max_value":62},{"ts":1608264311930,"particle":"pm_2_5","value":5,"max_value":62},{"ts":1608264713753,"particle":"pm_2_5","value":6,"max_value":62},{"ts":1608265114653,"particle":"pm_2_5","value":4,"max_value":62},{"ts":1608265516562,"particle":"pm_2_5","value":4,"max_value":62},{"ts":1608265918222,"particle":"pm_2_5","value":5,"max_value":62},{"ts":1608266319068,"particle":"pm_2_5","value":4,"max_value":62},{"ts":1608266719848,"particle":"pm_2_5","value":4,"max_value":62},{"ts":1608267120698,"particle":"pm_2_5","value":3,"max_value":62},{"ts":1608267521929,"particle":"pm_2_5","value":4,"max_value":62},{"ts":1608267922945,"particle":"pm_2_5","value":5,"max_value":62},{"ts":1608268324531,"particle":"pm_2_5","value":6,"max_value":62},{"ts":1608268725602,"particle":"pm_2_5","value":4,"max_value":62},{"ts":1608269126800,"particle":"pm_2_5","value":4,"max_value":62},{"ts":1608269528066,"particle":"pm_2_5","value":3,"max_value":62},{"ts":1608269929292,"particle":"pm_2_5","value":3,"max_value":62},{"ts":1608270332191,"particle":"pm_2_5","value":4,"max_value":62},{"ts":1608270733613,"particle":"pm_2_5","value":3,"max_value":62},{"ts":1608271136572,"particle":"pm_2_5","value":4,"max_value":62},{"ts":1608271537937,"particle":"pm_2_5","value":4,"max_value":62},{"ts":1608271939473,"particle":"pm_2_5","value":3,"max_value":62},{"ts":1608272341101,"particle":"pm_2_5","value":4,"max_value":62},{"ts":1608272742764,"particle":"pm_2_5","value":4,"max_value":62},{"ts":1608273144532,"particle":"pm_2_5","value":4,"max_value":62},{"ts":1608273546285,"particle":"pm_2_5","value":4,"max_value":62},{"ts":1608273948890,"particle":"pm_2_5","value":5,"max_value":62},{"ts":1608274350720,"particle":"pm_2_5","value":3,"max_value":62},{"ts":1608274752491,"particle":"pm_2_5","value":4,"max_value":62},{"ts":1608275154174,"particle":"pm_2_5","value":4,"max_value":62},{"ts":1608275556681,"particle":"pm_2_5","value":4,"max_value":62},{"ts":1608275957605,"particle":"pm_2_5","value":4,"max_value":62},{"ts":1608276358262,"particle":"pm_2_5","value":4,"max_value":62},{"ts":1608276758914,"particle":"pm_2_5","value":5,"max_value":62},{"ts":1608277161116,"particle":"pm_2_5","value":4,"max_value":62},{"ts":1608277562060,"particle":"pm_2_5","value":5,"max_value":62},{"ts":1608277963298,"particle":"pm_2_5","value":7,"max_value":62},{"ts":1608278364342,"particle":"pm_2_5","value":6,"max_value":62},{"ts":1608278765364,"particle":"pm_2_5","value":6,"max_value":62},{"ts":1608279166104,"particle":"pm_2_5","value":5,"max_value":62},{"ts":1608279567390,"particle":"pm_2_5","value":5,"max_value":62},{"ts":1608279970534,"particle":"pm_2_5","value":5,"max_value":62},{"ts":1608280372087,"particle":"pm_2_5","value":5,"max_value":62},{"ts":1608280773717,"particle":"pm_2_5","value":5,"max_value":62},{"ts":1608281175989,"particle":"pm_2_5","value":6,"max_value":62},{"ts":1608281577632,"particle":"pm_2_5","value":5,"max_value":62},{"ts":1608281980919,"particle":"pm_2_5","value":6,"max_value":62},{"ts":1608282384594,"particle":"pm_2_5","value":6,"max_value":62},{"ts":1608282787983,"particle":"pm_2_5","value":5,"max_value":62},{"ts":1608283189940,"particle":"pm_2_5","value":6,"max_value":62},{"ts":1608283591882,"particle":"pm_2_5","value":5,"max_value":62},{"ts":1608283997911,"particle":"pm_2_5","value":5,"max_value":62},{"ts":1608284399632,"particle":"pm_2_5","value":5,"max_value":62},{"ts":1608284801640,"particle":"pm_2_5","value":6,"max_value":62},{"ts":1608285203922,"particle":"pm_2_5","value":4,"max_value":62},{"ts":1608285607982,"particle":"pm_2_5","value":5,"max_value":62},{"ts":1608286010730,"particle":"pm_2_5","value":7,"max_value":62},{"ts":1608286411873,"particle":"pm_2_5","value":6,"max_value":62},{"ts":1608286816519,"particle":"pm_2_5","value":7,"max_value":62},{"ts":1608287217624,"particle":"pm_2_5","value":6,"max_value":62},{"ts":1608287618929,"particle":"pm_2_5","value":5,"max_value":62},{"ts":1608288020104,"particle":"pm_2_5","value":5,"max_value":62},{"ts":1608288421448,"particle":"pm_2_5","value":5,"max_value":62},{"ts":1608288824442,"particle":"pm_2_5","value":5,"max_value":62},{"ts":1608289226023,"particle":"pm_2_5","value":5,"max_value":62},{"ts":1608289627832,"particle":"pm_2_5","value":4,"max_value":62},{"ts":1608290029641,"particle":"pm_2_5","value":7,"max_value":62},{"ts":1608290431469,"particle":"pm_2_5","value":5,"max_value":62},{"ts":1608290833215,"particle":"pm_2_5","value":5,"max_value":62},{"ts":1608291236457,"particle":"pm_2_5","value":6,"max_value":62},{"ts":1608291638073,"particle":"pm_2_5","value":6,"max_value":62},{"ts":1608292040111,"particle":"pm_2_5","value":6,"max_value":62},{"ts":1608292442308,"particle":"pm_2_5","value":5,"max_value":62},{"ts":1608292843950,"particle":"pm_2_5","value":6,"max_value":62},{"ts":1608293245374,"particle":"pm_2_5","value":8,"max_value":62},{"ts":1608293648772,"particle":"pm_2_5","value":7,"max_value":62},{"ts":1608294050572,"particle":"pm_2_5","value":7,"max_value":62},{"ts":1608294452274,"particle":"pm_2_5","value":7,"max_value":62},{"ts":1608294854104,"particle":"pm_2_5","value":6,"max_value":62},{"ts":1608295256392,"particle":"pm_2_5","value":7,"max_value":62},{"ts":1608295658150,"particle":"pm_2_5","value":6,"max_value":62},{"ts":1608296059004,"particle":"pm_2_5","value":7,"max_value":62},{"ts":1608296461327,"particle":"pm_2_5","value":7,"max_value":62},{"ts":1608296862117,"particle":"pm_2_5","value":6,"max_value":62},{"ts":1608297263273,"particle":"pm_2_5","value":6,"max_value":62},{"ts":1608297665525,"particle":"pm_2_5","value":5,"max_value":62},{"ts":1608298065242,"particle":"pm_2_5","value":5,"max_value":62},{"ts":1608298466290,"particle":"pm_2_5","value":4,"max_value":62},{"ts":1608298867254,"particle":"pm_2_5","value":6,"max_value":62},{"ts":1608299268402,"particle":"pm_2_5","value":7,"max_value":62},{"ts":1608299669651,"particle":"pm_2_5","value":8,"max_value":62},{"ts":1608300070738,"particle":"pm_2_5","value":6,"max_value":62},{"ts":1608300472372,"particle":"pm_2_5","value":6,"max_value":62},{"ts":1608300874235,"particle":"pm_2_5","value":8,"max_value":62},{"ts":1608301276494,"particle":"pm_2_5","value":28,"max_value":62},{"ts":1608301679972,"particle":"pm_2_5","value":38,"max_value":62},{"ts":1608302083093,"particle":"pm_2_5","value":37,"max_value":62},{"ts":1608302487862,"particle":"pm_2_5","value":36,"max_value":62},{"ts":1608302890471,"particle":"pm_2_5","value":37,"max_value":62},{"ts":1608303292971,"particle":"pm_2_5","value":37,"max_value":62},{"ts":1608303697014,"particle":"pm_2_5","value":40,"max_value":62},{"ts":1608304099550,"particle":"pm_2_5","value":40,"max_value":62},{"ts":1608304503520,"particle":"pm_2_5","value":41,"max_value":62},{"ts":1608304906244,"particle":"pm_2_5","value":39,"max_value":62},{"ts":1608305309552,"particle":"pm_2_5","value":39,"max_value":62},{"ts":1608305714343,"particle":"pm_2_5","value":38,"max_value":62},{"ts":1608306115248,"particle":"pm_2_5","value":36,"max_value":62},{"ts":1608306516974,"particle":"pm_2_5","value":38,"max_value":62},{"ts":1608306919095,"particle":"pm_2_5","value":36,"max_value":62},{"ts":1608307321820,"particle":"pm_2_5","value":38,"max_value":62},{"ts":1608307724080,"particle":"pm_2_5","value":36,"max_value":62},{"ts":1608308125978,"particle":"pm_2_5","value":33,"max_value":62},{"ts":1608308526909,"particle":"pm_2_5","value":29,"max_value":62},{"ts":1608308930161,"particle":"pm_2_5","value":31,"max_value":62},{"ts":1608309331908,"particle":"pm_2_5","value":28,"max_value":62},{"ts":1608309733873,"particle":"pm_2_5","value":25,"max_value":62},{"ts":1608310136031,"particle":"pm_2_5","value":25,"max_value":62},{"ts":1608310537076,"particle":"pm_2_5","value":21,"max_value":62},{"ts":1608310940707,"particle":"pm_2_5","value":24,"max_value":62},{"ts":1608311341938,"particle":"pm_2_5","value":18,"max_value":62},{"ts":1608311744202,"particle":"pm_2_5","value":16,"max_value":62},{"ts":1608312146123,"particle":"pm_2_5","value":17,"max_value":62},{"ts":1608312548700,"particle":"pm_2_5","value":17,"max_value":62},{"ts":1608312952492,"particle":"pm_2_5","value":13,"max_value":62},{"ts":1608313354852,"particle":"pm_2_5","value":14,"max_value":62},{"ts":1608313757755,"particle":"pm_2_5","value":16,"max_value":62},{"ts":1608314161659,"particle":"pm_2_5","value":12,"max_value":62},{"ts":1608314563974,"particle":"pm_2_5","value":13,"max_value":62},{"ts":1608314965780,"particle":"pm_2_5","value":11,"max_value":62},{"ts":1608315369314,"particle":"pm_2_5","value":10,"max_value":62},{"ts":1608315770059,"particle":"pm_2_5","value":11,"max_value":62},{"ts":1608316171076,"particle":"pm_2_5","value":10,"max_value":62},{"ts":1608316572092,"particle":"pm_2_5","value":10,"max_value":62},{"ts":1608316971870,"particle":"pm_2_5","value":8,"max_value":62},{"ts":1608317372873,"particle":"pm_2_5","value":7,"max_value":62},{"ts":1608317775734,"particle":"pm_2_5","value":9,"max_value":62},{"ts":1608318177164,"particle":"pm_2_5","value":8,"max_value":62},{"ts":1608318578611,"particle":"pm_2_5","value":8,"max_value":62},{"ts":1608318981514,"particle":"pm_2_5","value":9,"max_value":62},{"ts":1608319383061,"particle":"pm_2_5","value":9,"max_value":62},{"ts":1608319784476,"particle":"pm_2_5","value":9,"max_value":62},{"ts":1608320186378,"particle":"pm_2_5","value":8,"max_value":62},{"ts":1608320589928,"particle":"pm_2_5","value":10,"max_value":62},{"ts":1608320995494,"particle":"pm_2_5","value":11,"max_value":62},{"ts":1608321397223,"particle":"pm_2_5","value":8,"max_value":62},{"ts":1608321799244,"particle":"pm_2_5","value":9,"max_value":62},{"ts":1608322201276,"particle":"pm_2_5","value":10,"max_value":62},{"ts":1608322603388,"particle":"pm_2_5","value":9,"max_value":62},{"ts":1608323005801,"particle":"pm_2_5","value":12,"max_value":62},{"ts":1608323407962,"particle":"pm_2_5","value":11,"max_value":62},{"ts":1608323809705,"particle":"pm_2_5","value":13,"max_value":62},{"ts":1608324211480,"particle":"pm_2_5","value":11,"max_value":62},{"ts":1608324613382,"particle":"pm_2_5","value":12,"max_value":62},{"ts":1608325015664,"particle":"pm_2_5","value":13,"max_value":62},{"ts":1608325418031,"particle":"pm_2_5","value":17,"max_value":62},{"ts":1608325818847,"particle":"pm_2_5","value":13,"max_value":62},{"ts":1608326222452,"particle":"pm_2_5","value":15,"max_value":62},{"ts":1608326623799,"particle":"pm_2_5","value":14,"max_value":62},{"ts":1608327025283,"particle":"pm_2_5","value":14,"max_value":62},{"ts":1608327426380,"particle":"pm_2_5","value":12,"max_value":62},{"ts":1608327828286,"particle":"pm_2_5","value":13,"max_value":62},{"ts":1608328230185,"particle":"pm_2_5","value":14,"max_value":62},{"ts":1608328631922,"particle":"pm_2_5","value":12,"max_value":62},{"ts":1608329033847,"particle":"pm_2_5","value":16,"max_value":62},{"ts":1608329436550,"particle":"pm_2_5","value":17,"max_value":62},{"ts":1608329839483,"particle":"pm_2_5","value":14,"max_value":62},{"ts":1608330241713,"particle":"pm_2_5","value":14,"max_value":62},{"ts":1608330643457,"particle":"pm_2_5","value":14,"max_value":62},{"ts":1608331045411,"particle":"pm_2_5","value":14,"max_value":62},{"ts":1608331447549,"particle":"pm_2_5","value":14,"max_value":62},{"ts":1608331849316,"particle":"pm_2_5","value":13,"max_value":62},{"ts":1608332252470,"particle":"pm_2_5","value":14,"max_value":62},{"ts":1608332654791,"particle":"pm_2_5","value":12,"max_value":62},{"ts":1608333056444,"particle":"pm_2_5","value":12,"max_value":62},{"ts":1608333458073,"particle":"pm_2_5","value":11,"max_value":62},{"ts":1608333861384,"particle":"pm_2_5","value":12,"max_value":62},{"ts":1608334262811,"particle":"pm_2_5","value":11,"max_value":62},{"ts":1608334666153,"particle":"pm_2_5","value":12,"max_value":62},{"ts":1608335067772,"particle":"pm_2_5","value":11,"max_value":62},{"ts":1608335469157,"particle":"pm_2_5","value":11,"max_value":62},{"ts":1608335869903,"particle":"pm_2_5","value":11,"max_value":62},{"ts":1608336270931,"particle":"pm_2_5","value":9,"max_value":62},{"ts":1608336672181,"particle":"pm_2_5","value":9,"max_value":62},{"ts":1608337074385,"particle":"pm_2_5","value":9,"max_value":62},{"ts":1608337475858,"particle":"pm_2_5","value":10,"max_value":62},{"ts":1608337876914,"particle":"pm_2_5","value":9,"max_value":62},{"ts":1608338278053,"particle":"pm_2_5","value":10,"max_value":62},{"ts":1608338679264,"particle":"pm_2_5","value":10,"max_value":62},{"ts":1608339082391,"particle":"pm_2_5","value":10,"max_value":62},{"ts":1608339483849,"particle":"pm_2_5","value":10,"max_value":62},{"ts":1608339885186,"particle":"pm_2_5","value":9,"max_value":62},{"ts":1608340286691,"particle":"pm_2_5","value":9,"max_value":62},{"ts":1608340688099,"particle":"pm_2_5","value":9,"max_value":62},{"ts":1608341089463,"particle":"pm_2_5","value":9,"max_value":62},{"ts":1608341491081,"particle":"pm_2_5","value":8,"max_value":62},{"ts":1608341892868,"particle":"pm_2_5","value":8,"max_value":62},{"ts":1608342295392,"particle":"pm_2_5","value":8,"max_value":62},{"ts":1608342697171,"particle":"pm_2_5","value":8,"max_value":62},{"ts":1608343098743,"particle":"pm_2_5","value":7,"max_value":62},{"ts":1608343500631,"particle":"pm_2_5","value":9,"max_value":62},{"ts":1608343902424,"particle":"pm_2_5","value":7,"max_value":62},{"ts":1608344305742,"particle":"pm_2_5","value":7,"max_value":62},{"ts":1608344707351,"particle":"pm_2_5","value":6,"max_value":62},{"ts":1608345108894,"particle":"pm_2_5","value":7,"max_value":62},{"ts":1608345510684,"particle":"pm_2_5","value":8,"max_value":62},{"ts":1608345911377,"particle":"pm_2_5","value":7,"max_value":62},{"ts":1608346312047,"particle":"pm_2_5","value":6,"max_value":62},{"ts":1608346714527,"particle":"pm_2_5","value":7,"max_value":62},{"ts":1608347116868,"particle":"pm_2_5","value":8,"max_value":62},{"ts":1608347517862,"particle":"pm_2_5","value":6,"max_value":62},{"ts":1608347918884,"particle":"pm_2_5","value":7,"max_value":62},{"ts":1608348320220,"particle":"pm_2_5","value":6,"max_value":62},{"ts":1608348721333,"particle":"pm_2_5","value":6,"max_value":62},{"ts":1608349123010,"particle":"pm_2_5","value":8,"max_value":62},{"ts":1608349524641,"particle":"pm_2_5","value":8,"max_value":62},{"ts":1608349926765,"particle":"pm_2_5","value":12,"max_value":62},{"ts":1608350329711,"particle":"pm_2_5","value":14,"max_value":62},{"ts":1608350732853,"particle":"pm_2_5","value":17,"max_value":62},{"ts":1608351134325,"particle":"pm_2_5","value":15,"max_value":62},{"ts":1608351535667,"particle":"pm_2_5","value":18,"max_value":62},{"ts":1608351937350,"particle":"pm_2_5","value":19,"max_value":62},{"ts":1608352339199,"particle":"pm_2_5","value":19,"max_value":62},{"ts":1608352742444,"particle":"pm_2_5","value":24,"max_value":62},{"ts":1608353144829,"particle":"pm_2_5","value":23,"max_value":62},{"ts":1608353548962,"particle":"pm_2_5","value":24,"max_value":62},{"ts":1608353951652,"particle":"pm_2_5","value":24,"max_value":62},{"ts":1608354354203,"particle":"pm_2_5","value":24,"max_value":62},{"ts":1608354757121,"particle":"pm_2_5","value":23,"max_value":62},{"ts":1608355159324,"particle":"pm_2_5","value":22,"max_value":62},{"ts":1608355562276,"particle":"pm_2_5","value":20,"max_value":62},{"ts":1608355964288,"particle":"pm_2_5","value":23,"max_value":62},{"ts":1608356367413,"particle":"pm_2_5","value":24,"max_value":62},{"ts":1608356768737,"particle":"pm_2_5","value":19,"max_value":62},{"ts":1608357172443,"particle":"pm_2_5","value":19,"max_value":62},{"ts":1608357574297,"particle":"pm_2_5","value":20,"max_value":62},{"ts":1608357975420,"particle":"pm_2_5","value":17,"max_value":62},{"ts":1608358377283,"particle":"pm_2_5","value":18,"max_value":62},{"ts":1608358780290,"particle":"pm_2_5","value":21,"max_value":62},{"ts":1608359183602,"particle":"pm_2_5","value":16,"max_value":62},{"ts":1608359586527,"particle":"pm_2_5","value":19,"max_value":62},{"ts":1608359988447,"particle":"pm_2_5","value":17,"max_value":62},{"ts":1608360389989,"particle":"pm_2_5","value":12,"max_value":62},{"ts":1608360794307,"particle":"pm_2_5","value":17,"max_value":62},{"ts":1608361195676,"particle":"pm_2_5","value":13,"max_value":62},{"ts":1608361597477,"particle":"pm_2_5","value":12,"max_value":62},{"ts":1608362000901,"particle":"pm_2_5","value":12,"max_value":62},{"ts":1608362402860,"particle":"pm_2_5","value":11,"max_value":62},{"ts":1608362804391,"particle":"pm_2_5","value":10,"max_value":62},{"ts":1608363206591,"particle":"pm_2_5","value":9,"max_value":62},{"ts":1608363609830,"particle":"pm_2_5","value":9,"max_value":62},{"ts":1608364011330,"particle":"pm_2_5","value":9,"max_value":62},{"ts":1608364415293,"particle":"pm_2_5","value":11,"max_value":62},{"ts":1608364816886,"particle":"pm_2_5","value":10,"max_value":62},{"ts":1608365217515,"particle":"pm_2_5","value":10,"max_value":62},{"ts":1608365618303,"particle":"pm_2_5","value":8,"max_value":62},{"ts":1608366019079,"particle":"pm_2_5","value":10,"max_value":62},{"ts":1608366420054,"particle":"pm_2_5","value":8,"max_value":62},{"ts":1608366821139,"particle":"pm_2_5","value":8,"max_value":62},{"ts":1608367223228,"particle":"pm_2_5","value":10,"max_value":62},{"ts":1608367624472,"particle":"pm_2_5","value":8,"max_value":62},{"ts":1608368025555,"particle":"pm_2_5","value":8,"max_value":62},{"ts":1608368426816,"particle":"pm_2_5","value":7,"max_value":62},{"ts":1608368828082,"particle":"pm_2_5","value":9,"max_value":62},{"ts":1608369229629,"particle":"pm_2_5","value":10,"max_value":62},{"ts":1608369631453,"particle":"pm_2_5","value":9,"max_value":62},{"ts":1608370033011,"particle":"pm_2_5","value":8,"max_value":62},{"ts":1608370434523,"particle":"pm_2_5","value":7,"max_value":62},{"ts":1608370836062,"particle":"pm_2_5","value":6,"max_value":62},{"ts":1608371237658,"particle":"pm_2_5","value":8,"max_value":62},{"ts":1608371639301,"particle":"pm_2_5","value":8,"max_value":62},{"ts":1608372040797,"particle":"pm_2_5","value":7,"max_value":62},{"ts":1608372442444,"particle":"pm_2_5","value":5,"max_value":62},{"ts":1608372847352,"particle":"pm_2_5","value":6,"max_value":62},{"ts":1608373249083,"particle":"pm_2_5","value":9,"max_value":62},{"ts":1608373651182,"particle":"pm_2_5","value":10,"max_value":62},{"ts":1608374052854,"particle":"pm_2_5","value":7,"max_value":62},{"ts":1608374454640,"particle":"pm_2_5","value":6,"max_value":62},{"ts":1608374855204,"particle":"pm_2_5","value":7,"max_value":62},{"ts":1608375255786,"particle":"pm_2_5","value":6,"max_value":62},{"ts":1608375656705,"particle":"pm_2_5","value":5,"max_value":62},{"ts":1608376057448,"particle":"pm_2_5","value":7,"max_value":62},{"ts":1608376458432,"particle":"pm_2_5","value":6,"max_value":62},{"ts":1608376859383,"particle":"pm_2_5","value":7,"max_value":62},{"ts":1608377260309,"particle":"pm_2_5","value":6,"max_value":62},{"ts":1608377661375,"particle":"pm_2_5","value":5,"max_value":62},{"ts":1608378062387,"particle":"pm_2_5","value":5,"max_value":62},{"ts":1608378463675,"particle":"pm_2_5","value":6,"max_value":62},{"ts":1608378864738,"particle":"pm_2_5","value":6,"max_value":62},{"ts":1608379267590,"particle":"pm_2_5","value":5,"max_value":62},{"ts":1608379668737,"particle":"pm_2_5","value":5,"max_value":62},{"ts":1608380070201,"particle":"pm_2_5","value":6,"max_value":62}]