[{"ts":1614453340938,"particle":"pm_10_0","value":16,"max_value":24},{"ts":1614453760703,"particle":"pm_10_0","value":15,"max_value":24},{"ts":1614454182160,"particle":"pm_10_0","value":15,"max_value":24},{"ts":1614454602841,"particle":"pm_10_0","value":15,"max_value":24},{"ts":1614455023374,"particle":"pm_10_0","value":15,"max_value":24},{"ts":1614455443217,"particle":"pm_10_0","value":12,"max_value":24},{"ts":1614455863267,"particle":"pm_10_0","value":12,"max_value":24},{"ts":1614456283656,"particle":"pm_10_0","value":12,"max_value":24},{"ts":1614456704050,"particle":"pm_10_0","value":14,"max_value":24},{"ts":1614457124409,"particle":"pm_10_0","value":13,"max_value":24},{"ts":1614457545280,"particle":"pm_10_0","value":11,"max_value":24},{"ts":1614457966980,"particle":"pm_10_0","value":13,"max_value":24},{"ts":1614458388199,"particle":"pm_10_0","value":11,"max_value":24},{"ts":1614458810185,"particle":"pm_10_0","value":13,"max_value":24},{"ts":1614459232359,"particle":"pm_10_0","value":13,"max_value":24},{"ts":1614459653409,"particle":"pm_10_0","value":12,"max_value":24},{"ts":1614460074603,"particle":"pm_10_0","value":12,"max_value":24},{"ts":1614460494928,"particle":"pm_10_0","value":11,"max_value":24},{"ts":1614460915809,"particle":"pm_10_0","value":15,"max_value":24},{"ts":1614461336655,"particle":"pm_10_0","value":14,"max_value":24},{"ts":1614461757138,"particle":"pm_10_0","value":12,"max_value":24},{"ts":1614462177791,"particle":"pm_10_0","value":13,"max_value":24},{"ts":1614462598654,"particle":"pm_10_0","value":14,"max_value":24},{"ts":1614463019668,"particle":"pm_10_0","value":14,"max_value":24},{"ts":1614463440330,"particle":"pm_10_0","value":15,"max_value":24},{"ts":1614464285278,"particle":"pm_10_0","value":15,"max_value":24},{"ts":1614464705355,"particle":"pm_10_0","value":15,"max_value":24},{"ts":1614465126231,"particle":"pm_10_0","value":18,"max_value":24},{"ts":1614465546286,"particle":"pm_10_0","value":16,"max_value":24},{"ts":1614465966974,"particle":"pm_10_0","value":16,"max_value":24},{"ts":1614466388180,"particle":"pm_10_0","value":19,"max_value":24},{"ts":1614466809014,"particle":"pm_10_0","value":16,"max_value":24},{"ts":1614467229123,"particle":"pm_10_0","value":17,"max_value":24},{"ts":1614467650230,"particle":"pm_10_0","value":19,"max_value":24},{"ts":1614468072167,"particle":"pm_10_0","value":18,"max_value":24},{"ts":1614468492934,"particle":"pm_10_0","value":20,"max_value":24},{"ts":1614468914557,"particle":"pm_10_0","value":18,"max_value":24},{"ts":1614469336092,"particle":"pm_10_0","value":18,"max_value":24},{"ts":1614469757852,"particle":"pm_10_0","value":19,"max_value":24},{"ts":1614470179966,"particle":"pm_10_0","value":20,"max_value":24},{"ts":1614470602189,"particle":"pm_10_0","value":20,"max_value":24},{"ts":1614471024525,"particle":"pm_10_0","value":19,"max_value":24},{"ts":1614471447699,"particle":"pm_10_0","value":20,"max_value":24},{"ts":1614471867853,"particle":"pm_10_0","value":19,"max_value":24},{"ts":1614472287719,"particle":"pm_10_0","value":19,"max_value":24},{"ts":1614472707519,"particle":"pm_10_0","value":18,"max_value":24},{"ts":1614473127511,"particle":"pm_10_0","value":20,"max_value":24},{"ts":1614473547461,"particle":"pm_10_0","value":17,"max_value":24},{"ts":1614473967541,"particle":"pm_10_0","value":21,"max_value":24},{"ts":1614474388040,"particle":"pm_10_0","value":23,"max_value":24},{"ts":1614474808509,"particle":"pm_10_0","value":21,"max_value":24},{"ts":1614475228860,"particle":"pm_10_0","value":20,"max_value":24},{"ts":1614506836793,"particle":"pm_10_0","value":24,"max_value":24},{"ts":1614507249845,"particle":"pm_10_0","value":20,"max_value":24},{"ts":1614507670763,"particle":"pm_10_0","value":18,"max_value":24},{"ts":1614508093059,"particle":"pm_10_0","value":20,"max_value":24},{"ts":1614508513181,"particle":"pm_10_0","value":16,"max_value":24},{"ts":1614508934078,"particle":"pm_10_0","value":19,"max_value":24},{"ts":1614509354523,"particle":"pm_10_0","value":15,"max_value":24},{"ts":1614509775509,"particle":"pm_10_0","value":16,"max_value":24},{"ts":1614510196723,"particle":"pm_10_0","value":16,"max_value":24},{"ts":1614510617282,"particle":"pm_10_0","value":17,"max_value":24},{"ts":1614511038534,"particle":"pm_10_0","value":14,"max_value":24},{"ts":1614511458411,"particle":"pm_10_0","value":14,"max_value":24},{"ts":1614511878819,"particle":"pm_10_0","value":13,"max_value":24},{"ts":1614512299301,"particle":"pm_10_0","value":15,"max_value":24},{"ts":1614512720396,"particle":"pm_10_0","value":13,"max_value":24},{"ts":1614513141483,"particle":"pm_10_0","value":11,"max_value":24},{"ts":1614513562389,"particle":"pm_10_0","value":12,"max_value":24},{"ts":1614513984185,"particle":"pm_10_0","value":10,"max_value":24},{"ts":1614514405804,"particle":"pm_10_0","value":13,"max_value":24},{"ts":1614514826247,"particle":"pm_10_0","value":11,"max_value":24},{"ts":1614515246858,"particle":"pm_10_0","value":10,"max_value":24},{"ts":1614515668304,"particle":"pm_10_0","value":12,"max_value":24},{"ts":1614516089703,"particle":"pm_10_0","value":11,"max_value":24},{"ts":1614517145557,"particle":"pm_10_0","value":10,"max_value":24},{"ts":1614517566996,"particle":"pm_10_0","value":12,"max_value":24},{"ts":1614517988285,"particle":"pm_10_0","value":13,"max_value":24},{"ts":1614531102456,"particle":"pm_10_0","value":0,"max_value":24},{"ts":1614531516687,"particle":"pm_10_0","value":0,"max_value":24},{"ts":1614531936188,"particle":"pm_10_0","value":0,"max_value":24},{"ts":1614532356242,"particle":"pm_10_0","value":0,"max_value":24},{"ts":1614532777332,"particle":"pm_10_0","value":0,"max_value":24},{"ts":1614533198479,"particle":"pm_10_0","value":0,"max_value":24},{"ts":1614533619492,"particle":"pm_10_0","value":0,"max_value":24},{"ts":1614534673415,"particle":"pm_10_0","value":0,"max_value":24},{"ts":1614535093185,"particle":"pm_10_0","value":0,"max_value":24},{"ts":1614535513232,"particle":"pm_10_0","value":0,"max_value":24},{"ts":1614535934103,"particle":"pm_10_0","value":0,"max_value":24},{"ts":1614536354034,"particle":"pm_10_0","value":0,"max_value":24},{"ts":1614536773860,"particle":"pm_10_0","value":0,"max_value":24},{"ts":1614537193834,"particle":"pm_10_0","value":0,"max_value":24},{"ts":1614537613761,"particle":"pm_10_0","value":0,"max_value":24},{"ts":1614538034401,"particle":"pm_10_0","value":0,"max_value":24},{"ts":1614538455255,"particle":"pm_10_0","value":0,"max_value":24},{"ts":1614538876553,"particle":"pm_10_0","value":0,"max_value":24},{"ts":1614539297663,"particle":"pm_10_0","value":0,"max_value":24},{"ts":1614539718902,"particle":"pm_10_0","value":0,"max_value":24},{"ts":1614540140089,"particle":"pm_10_0","value":0,"max_value":24},{"ts":1614540561120,"particle":"pm_10_0","value":0,"max_value":24},{"ts":1614540982725,"particle":"pm_10_0","value":0,"max_value":24},{"ts":1614453340938,"particle":"pm_1_0","value":8,"max_value":24},{"ts":1614453760703,"particle":"pm_1_0","value":9,"max_value":24},{"ts":1614454182160,"particle":"pm_1_0","value":8,"max_value":24},{"ts":1614454602841,"particle":"pm_1_0","value":8,"max_value":24},{"ts":1614455023374,"particle":"pm_1_0","value":8,"max_value":24},{"ts":1614455443217,"particle":"pm_1_0","value":7,"max_value":24},{"ts":1614455863267,"particle":"pm_1_0","value":7,"max_value":24},{"ts":1614456283656,"particle":"pm_1_0","value":7,"max_value":24},{"ts":1614456704050,"particle":"pm_1_0","value":6,"max_value":24},{"ts":1614457124409,"particle":"pm_1_0","value":7,"max_value":24},{"ts":1614457545280,"particle":"pm_1_0","value":6,"max_value":24},{"ts":1614457966980,"particle":"pm_1_0","value":7,"max_value":24},{"ts":1614458388199,"particle":"pm_1_0","value":6,"max_value":24},{"ts":1614458810185,"particle":"pm_1_0","value":6,"max_value":24},{"ts":1614459232359,"particle":"pm_1_0","value":6,"max_value":24},{"ts":1614459653409,"particle":"pm_1_0","value":6,"max_value":24},{"ts":1614460074603,"particle":"pm_1_0","value":6,"max_value":24},{"ts":1614460494928,"particle":"pm_1_0","value":7,"max_value":24},{"ts":1614460915809,"particle":"pm_1_0","value":7,"max_value":24},{"ts":1614461336655,"particle":"pm_1_0","value":8,"max_value":24},{"ts":1614461757138,"particle":"pm_1_0","value":7,"max_value":24},{"ts":1614462177791,"particle":"pm_1_0","value":8,"max_value":24},{"ts":1614462598654,"particle":"pm_1_0","value":8,"max_value":24},{"ts":1614463019668,"particle":"pm_1_0","value":8,"max_value":24},{"ts":1614463440330,"particle":"pm_1_0","value":9,"max_value":24},{"ts":1614464285278,"particle":"pm_1_0","value":9,"max_value":24},{"ts":1614464705355,"particle":"pm_1_0","value":8,"max_value":24},{"ts":1614465126231,"particle":"pm_1_0","value":9,"max_value":24},{"ts":1614465546286,"particle":"pm_1_0","value":10,"max_value":24},{"ts":1614465966974,"particle":"pm_1_0","value":9,"max_value":24},{"ts":1614466388180,"particle":"pm_1_0","value":10,"max_value":24},{"ts":1614466809014,"particle":"pm_1_0","value":11,"max_value":24},{"ts":1614467229123,"particle":"pm_1_0","value":10,"max_value":24},{"ts":1614467650230,"particle":"pm_1_0","value":10,"max_value":24},{"ts":1614468072167,"particle":"pm_1_0","value":11,"max_value":24},{"ts":1614468492934,"particle":"pm_1_0","value":11,"max_value":24},{"ts":1614468914557,"particle":"pm_1_0","value":10,"max_value":24},{"ts":1614469336092,"particle":"pm_1_0","value":11,"max_value":24},{"ts":1614469757852,"particle":"pm_1_0","value":11,"max_value":24},{"ts":1614470179966,"particle":"pm_1_0","value":11,"max_value":24},{"ts":1614470602189,"particle":"pm_1_0","value":11,"max_value":24},{"ts":1614471024525,"particle":"pm_1_0","value":11,"max_value":24},{"ts":1614471447699,"particle":"pm_1_0","value":12,"max_value":24},{"ts":1614471867853,"particle":"pm_1_0","value":11,"max_value":24},{"ts":1614472287719,"particle":"pm_1_0","value":11,"max_value":24},{"ts":1614472707519,"particle":"pm_1_0","value":11,"max_value":24},{"ts":1614473127511,"particle":"pm_1_0","value":11,"max_value":24},{"ts":1614473547461,"particle":"pm_1_0","value":11,"max_value":24},{"ts":1614473967541,"particle":"pm_1_0","value":12,"max_value":24},{"ts":1614474388040,"particle":"pm_1_0","value":12,"max_value":24},{"ts":1614474808509,"particle":"pm_1_0","value":12,"max_value":24},{"ts":1614475228860,"particle":"pm_1_0","value":12,"max_value":24},{"ts":1614506836793,"particle":"pm_1_0","value":11,"max_value":24},{"ts":1614507249845,"particle":"pm_1_0","value":10,"max_value":24},{"ts":1614507670763,"particle":"pm_1_0","value":10,"max_value":24},{"ts":1614508093059,"particle":"pm_1_0","value":10,"max_value":24},{"ts":1614508513181,"particle":"pm_1_0","value":9,"max_value":24},{"ts":1614508934078,"particle":"pm_1_0","value":10,"max_value":24},{"ts":1614509354523,"particle":"pm_1_0","value":8,"max_value":24},{"ts":1614509775509,"particle":"pm_1_0","value":9,"max_value":24},{"ts":1614510196723,"particle":"pm_1_0","value":9,"max_value":24},{"ts":1614510617282,"particle":"pm_1_0","value":9,"max_value":24},{"ts":1614511038534,"particle":"pm_1_0","value":7,"max_value":24},{"ts":1614511458411,"particle":"pm_1_0","value":7,"max_value":24},{"ts":1614511878819,"particle":"pm_1_0","value":7,"max_value":24},{"ts":1614512299301,"particle":"pm_1_0","value":8,"max_value":24},{"ts":1614512720396,"particle":"pm_1_0","value":7,"max_value":24},{"ts":1614513141483,"particle":"pm_1_0","value":6,"max_value":24},{"ts":1614513562389,"particle":"pm_1_0","value":7,"max_value":24},{"ts":1614513984185,"particle":"pm_1_0","value":6,"max_value":24},{"ts":1614514405804,"particle":"pm_1_0","value":7,"max_value":24},{"ts":1614514826247,"particle":"pm_1_0","value":7,"max_value":24},{"ts":1614515246858,"particle":"pm_1_0","value":6,"max_value":24},{"ts":1614515668304,"particle":"pm_1_0","value":7,"max_value":24},{"ts":1614516089703,"particle":"pm_1_0","value":6,"max_value":24},{"ts":1614517145557,"particle":"pm_1_0","value":6,"max_value":24},{"ts":1614517566996,"particle":"pm_1_0","value":7,"max_value":24},{"ts":1614517988285,"particle":"pm_1_0","value":8,"max_value":24},{"ts":1614531102456,"particle":"pm_1_0","value":0,"max_value":24},{"ts":1614531516687,"particle":"pm_1_0","value":0,"max_value":24},{"ts":1614531936188,"particle":"pm_1_0","value":0,"max_value":24},{"ts":1614532356242,"particle":"pm_1_0","value":0,"max_value":24},{"ts":1614532777332,"particle":"pm_1_0","value":0,"max_value":24},{"ts":1614533198479,"particle":"pm_1_0","value":0,"max_value":24},{"ts":1614533619492,"particle":"pm_1_0","value":0,"max_value":24},{"ts":1614534673415,"particle":"pm_1_0","value":0,"max_value":24},{"ts":1614535093185,"particle":"pm_1_0","value":0,"max_value":24},{"ts":1614535513232,"particle":"pm_1_0","value":0,"max_value":24},{"ts":1614535934103,"particle":"pm_1_0","value":0,"max_value":24},{"ts":1614536354034,"particle":"pm_1_0","value":0,"max_value":24},{"ts":1614536773860,"particle":"pm_1_0","value":0,"max_value":24},{"ts":1614537193834,"particle":"pm_1_0","value":0,"max_value":24},{"ts":1614537613761,"particle":"pm_1_0","value":0,"max_value":24},{"ts":1614538034401,"particle":"pm_1_0","value":0,"max_value":24},{"ts":1614538455255,"particle":"pm_1_0","value":0,"max_value":24},{"ts":1614538876553,"particle":"pm_1_0","value":0,"max_value":24},{"ts":1614539297663,"particle":"pm_1_0","value":0,"max_value":24},{"ts":1614539718902,"particle":"pm_1_0","value":0,"max_value":24},{"ts":1614540140089,"particle":"pm_1_0","value":0,"max_value":24},{"ts":1614540561120,"particle":"pm_1_0","value":0,"max_value":24},{"ts":1614540982725,"particle":"pm_1_0","value":0,"max_value":24},{"ts":1614453340938,"particle":"pm_2_5","value":15,"max_value":24},{"ts":1614453760703,"particle":"pm_2_5","value":14,"max_value":24},{"ts":1614454182160,"particle":"pm_2_5","value":14,"max_value":24},{"ts":1614454602841,"particle":"pm_2_5","value":14,"max_value":24},{"ts":1614455023374,"particle":"pm_2_5","value":14,"max_value":24},{"ts":1614455443217,"particle":"pm_2_5","value":12,"max_value":24},{"ts":1614455863267,"particle":"pm_2_5","value":11,"max_value":24},{"ts":1614456283656,"particle":"pm_2_5","value":12,"max_value":24},{"ts":1614456704050,"particle":"pm_2_5","value":13,"max_value":24},{"ts":1614457124409,"particle":"pm_2_5","value":11,"max_value":24},{"ts":1614457545280,"particle":"pm_2_5","value":10,"max_value":24},{"ts":1614457966980,"particle":"pm_2_5","value":12,"max_value":24},{"ts":1614458388199,"particle":"pm_2_5","value":11,"max_value":24},{"ts":1614458810185,"particle":"pm_2_5","value":12,"max_value":24},{"ts":1614459232359,"particle":"pm_2_5","value":12,"max_value":24},{"ts":1614459653409,"particle":"pm_2_5","value":11,"max_value":24},{"ts":1614460074603,"particle":"pm_2_5","value":10,"max_value":24},{"ts":1614460494928,"particle":"pm_2_5","value":11,"max_value":24},{"ts":1614460915809,"particle":"pm_2_5","value":13,"max_value":24},{"ts":1614461336655,"particle":"pm_2_5","value":13,"max_value":24},{"ts":1614461757138,"particle":"pm_2_5","value":11,"max_value":24},{"ts":1614462177791,"particle":"pm_2_5","value":13,"max_value":24},{"ts":1614462598654,"particle":"pm_2_5","value":13,"max_value":24},{"ts":1614463019668,"particle":"pm_2_5","value":13,"max_value":24},{"ts":1614463440330,"particle":"pm_2_5","value":15,"max_value":24},{"ts":1614464285278,"particle":"pm_2_5","value":14,"max_value":24},{"ts":1614464705355,"particle":"pm_2_5","value":14,"max_value":24},{"ts":1614465126231,"particle":"pm_2_5","value":16,"max_value":24},{"ts":1614465546286,"particle":"pm_2_5","value":15,"max_value":24},{"ts":1614465966974,"particle":"pm_2_5","value":15,"max_value":24},{"ts":1614466388180,"particle":"pm_2_5","value":18,"max_value":24},{"ts":1614466809014,"particle":"pm_2_5","value":16,"max_value":24},{"ts":1614467229123,"particle":"pm_2_5","value":16,"max_value":24},{"ts":1614467650230,"particle":"pm_2_5","value":17,"max_value":24},{"ts":1614468072167,"particle":"pm_2_5","value":17,"max_value":24},{"ts":1614468492934,"particle":"pm_2_5","value":18,"max_value":24},{"ts":1614468914557,"particle":"pm_2_5","value":17,"max_value":24},{"ts":1614469336092,"particle":"pm_2_5","value":17,"max_value":24},{"ts":1614469757852,"particle":"pm_2_5","value":18,"max_value":24},{"ts":1614470179966,"particle":"pm_2_5","value":18,"max_value":24},{"ts":1614470602189,"particle":"pm_2_5","value":18,"max_value":24},{"ts":1614471024525,"particle":"pm_2_5","value":18,"max_value":24},{"ts":1614471447699,"particle":"pm_2_5","value":19,"max_value":24},{"ts":1614471867853,"particle":"pm_2_5","value":18,"max_value":24},{"ts":1614472287719,"particle":"pm_2_5","value":18,"max_value":24},{"ts":1614472707519,"particle":"pm_2_5","value":17,"max_value":24},{"ts":1614473127511,"particle":"pm_2_5","value":18,"max_value":24},{"ts":1614473547461,"particle":"pm_2_5","value":16,"max_value":24},{"ts":1614473967541,"particle":"pm_2_5","value":19,"max_value":24},{"ts":1614474388040,"particle":"pm_2_5","value":21,"max_value":24},{"ts":1614474808509,"particle":"pm_2_5","value":19,"max_value":24},{"ts":1614475228860,"particle":"pm_2_5","value":19,"max_value":24},{"ts":1614506836793,"particle":"pm_2_5","value":21,"max_value":24},{"ts":1614507249845,"particle":"pm_2_5","value":18,"max_value":24},{"ts":1614507670763,"particle":"pm_2_5","value":17,"max_value":24},{"ts":1614508093059,"particle":"pm_2_5","value":18,"max_value":24},{"ts":1614508513181,"particle":"pm_2_5","value":15,"max_value":24},{"ts":1614508934078,"particle":"pm_2_5","value":17,"max_value":24},{"ts":1614509354523,"particle":"pm_2_5","value":14,"max_value":24},{"ts":1614509775509,"particle":"pm_2_5","value":15,"max_value":24},{"ts":1614510196723,"particle":"pm_2_5","value":16,"max_value":24},{"ts":1614510617282,"particle":"pm_2_5","value":16,"max_value":24},{"ts":1614511038534,"particle":"pm_2_5","value":13,"max_value":24},{"ts":1614511458411,"particle":"pm_2_5","value":12,"max_value":24},{"ts":1614511878819,"particle":"pm_2_5","value":12,"max_value":24},{"ts":1614512299301,"particle":"pm_2_5","value":13,"max_value":24},{"ts":1614512720396,"particle":"pm_2_5","value":12,"max_value":24},{"ts":1614513141483,"particle":"pm_2_5","value":10,"max_value":24},{"ts":1614513562389,"particle":"pm_2_5","value":11,"max_value":24},{"ts":1614513984185,"particle":"pm_2_5","value":10,"max_value":24},{"ts":1614514405804,"particle":"pm_2_5","value":12,"max_value":24},{"ts":1614514826247,"particle":"pm_2_5","value":10,"max_value":24},{"ts":1614515246858,"particle":"pm_2_5","value":10,"max_value":24},{"ts":1614515668304,"particle":"pm_2_5","value":11,"max_value":24},{"ts":1614516089703,"particle":"pm_2_5","value":11,"max_value":24},{"ts":1614517145557,"particle":"pm_2_5","value":10,"max_value":24},{"ts":1614517566996,"particle":"pm_2_5","value":12,"max_value":24},{"ts":1614517988285,"particle":"pm_2_5","value":13,"max_value":24},{"ts":1614531102456,"particle":"pm_2_5","value":0,"max_value":24},{"ts":1614531516687,"particle":"pm_2_5","value":0,"max_value":24},{"ts":1614531936188,"particle":"pm_2_5","value":0,"max_value":24},{"ts":1614532356242,"particle":"pm_2_5","value":0,"max_value":24},{"ts":1614532777332,"particle":"pm_2_5","value":0,"max_value":24},{"ts":1614533198479,"particle":"pm_2_5","value":0,"max_value":24},{"ts":1614533619492,"particle":"pm_2_5","value":0,"max_value":24},{"ts":1614534673415,"particle":"pm_2_5","value":0,"max_value":24},{"ts":1614535093185,"particle":"pm_2_5","value":0,"max_value":24},{"ts":1614535513232,"particle":"pm_2_5","value":0,"max_value":24},{"ts":1614535934103,"particle":"pm_2_5","value":0,"max_value":24},{"ts":1614536354034,"particle":"pm_2_5","value":0,"max_value":24},{"ts":1614536773860,"particle":"pm_2_5","value":0,"max_value":24},{"ts":1614537193834,"particle":"pm_2_5","value":0,"max_value":24},{"ts":1614537613761,"particle":"pm_2_5","value":0,"max_value":24},{"ts":1614538034401,"particle":"pm_2_5","value":0,"max_value":24},{"ts":1614538455255,"particle":"pm_2_5","value":0,"max_value":24},{"ts":1614538876553,"particle":"pm_2_5","value":0,"max_value":24},{"ts":1614539297663,"particle":"pm_2_5","value":0,"max_value":24},{"ts":1614539718902,"particle":"pm_2_5","value":0,"max_value":24},{"ts":1614540140089,"particle":"pm_2_5","value":0,"max_value":24},{"ts":1614540561120,"particle":"pm_2_5","value":0,"max_value":24},{"ts":1614540982725,"particle":"pm_2_5","value":0,"max_value":24}]